[
  {
    "name": "حاز الأمير عن البرية منصلا",
    "quafia": "q-ء",
    "engSea": "el-kamel",
    "arabSea": "الكامل",
    "engTopic": "Praise",
    "arabTopic": "قصائد مدح",
    "poetId": 1805,
    "type": "عموديه",
    "order": 1,
    "link": "https://www.aldiwan.net/poem71324.html",
    "id": 74201
  },
  {
    "name": "ومدامة يخفى النهار لنورها",
    "quafia": "q-ئ",
    "engSea": "el-kamel",
    "arabSea": "الكامل",
    "engTopic": "Romance",
    "arabTopic": "قصائد رومنسيه",
    "poetId": 1805,
    "type": "عموديه",
    "order": 2,
    "link": "https://www.aldiwan.net/poem71323.html",
    "id": 74202
  },
  {
    "name": "ومهند عضب إذا ما سل في",
    "quafia": "q-د",
    "engSea": "el-kamel",
    "arabSea": "الكامل",
    "engTopic": "Romance",
    "arabTopic": "قصائد رومنسيه",
    "poetId": 1805,
    "type": "عموديه",
    "order": 3,
    "link": "https://www.aldiwan.net/poem71322.html",
    "id": 74203
  },
  {
    "name": "وقهوة أطيب من نيل المنى",
    "quafia": "q-ف",
    "engSea": "el-rijz",
    "arabSea": "الرجز",
    "engTopic": "Short",
    "arabTopic": "قصائد قصيره",
    "poetId": 1805,
    "type": "عموديه",
    "order": 4,
    "link": "https://www.aldiwan.net/poem71321.html",
    "id": 74204
  },
  {
    "name": "متعاشقان مكاتمان هواهما",
    "quafia": "q-ب",
    "engSea": "el-kamel",
    "arabSea": "الكامل",
    "engTopic": "Romance",
    "arabTopic": "قصائد رومنسيه",
    "poetId": 1805,
    "type": "عموديه",
    "order": 5,
    "link": "https://www.aldiwan.net/poem71320.html",
    "id": 74205
  },
  {
    "name": "إني ليهجرني الصديق تجنيا",
    "quafia": "q-ب",
    "engSea": "el-kamel",
    "arabSea": "الكامل",
    "engTopic": "Reproach",
    "arabTopic": "قصائد عتاب",
    "poetId": 1805,
    "type": "عموديه",
    "order": 6,
    "link": "https://www.aldiwan.net/poem71319.html",
    "id": 74206
  },
  {
    "name": "وعاد الأوابد قبل الصباح",
    "quafia": "q-ب",
    "engSea": "el-mota9areb",
    "arabSea": "المتقارب",
    "engTopic": "Romance",
    "arabTopic": "قصائد رومنسيه",
    "poetId": 1805,
    "type": "عموديه",
    "order": 7,
    "link": "https://www.aldiwan.net/poem71318.html",
    "id": 74207
  },
  {
    "name": "إن رمت وصف الراح فأت بما",
    "quafia": "q-ب",
    "engSea": "ahd-el-kamel",
    "arabSea": "أحذ الكامل",
    "engTopic": "Romance",
    "arabTopic": "قصائد رومنسيه",
    "poetId": 1805,
    "type": "عموديه",
    "order": 8,
    "link": "https://www.aldiwan.net/poem71317.html",
    "id": 74208
  },
  {
    "name": "لها جيد ظبي واهتزاز يراعة",
    "quafia": "q-ب",
    "engSea": "el-tawil",
    "arabSea": "الطويل",
    "engTopic": "Satire",
    "arabTopic": "قصائد هجاء",
    "poetId": 1805,
    "type": "عموديه",
    "order": 9,
    "link": "https://www.aldiwan.net/poem71316.html",
    "id": 74209
  },
  {
    "name": "من يحتمل ثقل من يأتيه معتفيا",
    "quafia": "q-ب",
    "engSea": "bassit",
    "arabSea": "البسيط",
    "engTopic": "Satire",
    "arabTopic": "قصائد هجاء",
    "poetId": 1805,
    "type": "عموديه",
    "order": 10,
    "link": "https://www.aldiwan.net/poem71315.html",
    "id": 74210
  },
  {
    "name": "مدحت رسول الله أبغي بمدحه",
    "quafia": "q-ب",
    "engSea": "el-tawil",
    "arabSea": "الطويل",
    "engTopic": "Elegy",
    "arabTopic": "قصائد رثاء",
    "poetId": 1805,
    "type": "عموديه",
    "order": 11,
    "link": "https://www.aldiwan.net/poem71314.html",
    "id": 74211
  },
  {
    "name": "ولما رأين البين زمت ركابه",
    "quafia": "q-ب",
    "engSea": "el-tawil",
    "arabSea": "الطويل",
    "engTopic": "Satire",
    "arabTopic": "قصائد هجاء",
    "poetId": 1805,
    "type": "عموديه",
    "order": 12,
    "link": "https://www.aldiwan.net/poem71313.html",
    "id": 74212
  },
  {
    "name": "وردت عليها والنجوم كأنها",
    "quafia": "q-ب",
    "engSea": "el-tawil",
    "arabSea": "الطويل",
    "engTopic": "Short",
    "arabTopic": "قصائد قصيره",
    "poetId": 1805,
    "type": "عموديه",
    "order": 13,
    "link": "https://www.aldiwan.net/poem71312.html",
    "id": 74213
  },
  {
    "name": "غدوت في يوم ضريب أشهب",
    "quafia": "q-ب",
    "engSea": "el-rijz",
    "arabSea": "الرجز",
    "engTopic": "Short",
    "arabTopic": "قصائد قصيره",
    "poetId": 1805,
    "type": "عموديه",
    "order": 14,
    "link": "https://www.aldiwan.net/poem71311.html",
    "id": 74214
  },
  {
    "name": "قد أغتدي والليل في حجابه",
    "quafia": "q-ب",
    "engSea": "el-rijz",
    "arabSea": "الرجز",
    "engTopic": "Satire",
    "arabTopic": "قصائد هجاء",
    "poetId": 1805,
    "type": "عموديه",
    "order": 15,
    "link": "https://www.aldiwan.net/poem71310.html",
    "id": 74215
  },
  {
    "name": "يا رب كلب أهله في كسبه",
    "quafia": "q-ب",
    "engSea": "el-rijz",
    "arabSea": "الرجز",
    "engTopic": "Romance",
    "arabTopic": "قصائد رومنسيه",
    "poetId": 1805,
    "type": "عموديه",
    "order": 16,
    "link": "https://www.aldiwan.net/poem71309.html",
    "id": 74216
  },
  {
    "name": "أَخص الصفات التي",
    "quafia": "q-ب",
    "engSea": "majzoua-el-mota9areb",
    "arabSea": "مجزوء المتقارب",
    "engTopic": "Satire",
    "arabTopic": "قصائد هجاء",
    "poetId": 1805,
    "type": "عموديه",
    "order": 17,
    "link": "https://www.aldiwan.net/poem71308.html",
    "id": 74217
  },
  {
    "name": "نارنجة في فروع الدوح قد نظمت",
    "quafia": "q-ت",
    "engSea": "bassit",
    "arabSea": "البسيط",
    "engTopic": "Elegy",
    "arabTopic": "قصائد رثاء",
    "poetId": 1805,
    "type": "عموديه",
    "order": 18,
    "link": "https://www.aldiwan.net/poem71307.html",
    "id": 74218
  },
  {
    "name": "أعددت للندمان صيد زمج",
    "quafia": "q-ج",
    "engSea": "el-rijz",
    "arabSea": "الرجز",
    "engTopic": "Satire",
    "arabTopic": "قصائد هجاء",
    "poetId": 1805,
    "type": "عموديه",
    "order": 19,
    "link": "https://www.aldiwan.net/poem71306.html",
    "id": 74219
  },
  {
    "name": "لما تفرى الليلث عن أثباجه",
    "quafia": "q-ج",
    "engSea": "el-rijz",
    "arabSea": "الرجز",
    "engTopic": "Satire",
    "arabTopic": "قصائد هجاء",
    "poetId": 1805,
    "type": "عموديه",
    "order": 20,
    "link": "https://www.aldiwan.net/poem71305.html",
    "id": 74220
  },
  {
    "name": "إن اليئايئ اخف الطير أرواحا",
    "quafia": "q-ح",
    "engSea": "el-tawil",
    "arabSea": "الطويل",
    "engTopic": "Satire",
    "arabTopic": "قصائد هجاء",
    "poetId": 1805,
    "type": "عموديه",
    "order": 21,
    "link": "https://www.aldiwan.net/poem71304.html",
    "id": 74221
  },
  {
    "name": "راح إذا علت الأكف كؤوسها",
    "quafia": "q-ح",
    "engSea": "el-kamel",
    "arabSea": "الكامل",
    "engTopic": "Romance",
    "arabTopic": "قصائد رومنسيه",
    "poetId": 1805,
    "type": "عموديه",
    "order": 22,
    "link": "https://www.aldiwan.net/poem71303.html",
    "id": 74222
  },
  {
    "name": "من كان بالصيد كسابا فقانصه",
    "quafia": "q-د",
    "engSea": "bassit",
    "arabSea": "البسيط",
    "engTopic": "Satire",
    "arabTopic": "قصائد هجاء",
    "poetId": 1805,
    "type": "عموديه",
    "order": 23,
    "link": "https://www.aldiwan.net/poem71302.html",
    "id": 74223
  },
  {
    "name": "وكان لنا أصدقاء حماة",
    "quafia": "q-د",
    "engSea": "el-mota9areb",
    "arabSea": "المتقارب",
    "engTopic": "Short",
    "arabTopic": "قصائد قصيره",
    "poetId": 1805,
    "type": "عموديه",
    "order": 24,
    "link": "https://www.aldiwan.net/poem71301.html",
    "id": 74224
  },
  {
    "name": "خلقت كما أرادتك المعالي",
    "quafia": "q-د",
    "engSea": "el-kamel",
    "arabSea": "الكامل",
    "engTopic": "Short",
    "arabTopic": "قصائد قصيره",
    "poetId": 1805,
    "type": "عموديه",
    "order": 25,
    "link": "https://www.aldiwan.net/poem71300.html",
    "id": 74225
  },
  {
    "name": "عيناك شاهدتان أنك من",
    "quafia": "q-د",
    "engSea": "ahd-el-kamel",
    "arabSea": "أحذ الكامل",
    "engTopic": "Short",
    "arabTopic": "قصائد قصيره",
    "poetId": 1805,
    "type": "عموديه",
    "order": 26,
    "link": "https://www.aldiwan.net/poem71299.html",
    "id": 74226
  },
  {
    "name": "فلو شهد مقاماتي وأنديتي",
    "quafia": "q-د",
    "engSea": "bassit",
    "arabSea": "البسيط",
    "engTopic": "Elegy",
    "arabTopic": "قصائد رثاء",
    "poetId": 1805,
    "type": "عموديه",
    "order": 27,
    "link": "https://www.aldiwan.net/poem71298.html",
    "id": 74227
  },
  {
    "name": "إذا المرء أحمى نفسه كل شهوة",
    "quafia": "q-د",
    "engSea": "el-tawil",
    "arabSea": "الطويل",
    "engTopic": "Elegy",
    "arabTopic": "قصائد رثاء",
    "poetId": 1805,
    "type": "عموديه",
    "order": 28,
    "link": "https://www.aldiwan.net/poem71297.html",
    "id": 74228
  },
  {
    "name": "ومدامة لا يبتغي من ربه",
    "quafia": "q-د",
    "engSea": "el-kamel",
    "arabSea": "الكامل",
    "engTopic": "Elegy",
    "arabTopic": "قصائد رثاء",
    "poetId": 1805,
    "type": "عموديه",
    "order": 29,
    "link": "https://www.aldiwan.net/poem71296.html",
    "id": 74229
  },
  {
    "name": "جيش يفوت الظن حتى لا يرى",
    "quafia": "q-د",
    "engSea": "el-kamel",
    "arabSea": "الكامل",
    "engTopic": "Satire",
    "arabTopic": "قصائد هجاء",
    "poetId": 1805,
    "type": "عموديه",
    "order": 30,
    "link": "https://www.aldiwan.net/poem71295.html",
    "id": 74230
  },
  {
    "name": "أبا يوسف إني نظرت فلم أجد",
    "quafia": "q-د",
    "engSea": "el-tawil",
    "arabSea": "الطويل",
    "engTopic": "Praise",
    "arabTopic": "قصائد مدح",
    "poetId": 1805,
    "type": "عموديه",
    "order": 31,
    "link": "https://www.aldiwan.net/poem71294.html",
    "id": 74231
  },
  {
    "name": "لا شيء أحسن يا قناص من صرد",
    "quafia": "q-د",
    "engSea": "bassit",
    "arabSea": "البسيط",
    "engTopic": "Elegy",
    "arabTopic": "قصائد رثاء",
    "poetId": 1805,
    "type": "عموديه",
    "order": 32,
    "link": "https://www.aldiwan.net/poem71293.html",
    "id": 74232
  },
  {
    "name": "والكرم من كرم الطباع وفضلها",
    "quafia": "q-د",
    "engSea": "el-kamel",
    "arabSea": "الكامل",
    "engTopic": "Elegy",
    "arabTopic": "قصائد رثاء",
    "poetId": 1805,
    "type": "عموديه",
    "order": 33,
    "link": "https://www.aldiwan.net/poem71292.html",
    "id": 74233
  },
  {
    "name": "بانت سعاد وكانت بيضة البلد",
    "quafia": "q-د",
    "engSea": "bassit",
    "arabSea": "البسيط",
    "engTopic": "Elegy",
    "arabTopic": "قصائد رثاء",
    "poetId": 1805,
    "type": "عموديه",
    "order": 34,
    "link": "https://www.aldiwan.net/poem71291.html",
    "id": 74234
  },
  {
    "name": "كأن أطاريف الخضاب بكفها",
    "quafia": "q-د",
    "engSea": "el-tawil",
    "arabSea": "الطويل",
    "engTopic": "Short",
    "arabTopic": "قصائد قصيره",
    "poetId": 1805,
    "type": "عموديه",
    "order": 35,
    "link": "https://www.aldiwan.net/poem71290.html",
    "id": 74235
  },
  {
    "name": "ما جليد يوم النوى بجليد",
    "quafia": "q-د",
    "engSea": "el-khafif",
    "arabSea": "الخفيف",
    "engTopic": "Elegy",
    "arabTopic": "قصائد رثاء",
    "poetId": 1805,
    "type": "عموديه",
    "order": 36,
    "link": "https://www.aldiwan.net/poem71289.html",
    "id": 74236
  },
  {
    "name": "لدى إقحوانات حففن بناصح",
    "quafia": "q-د",
    "engSea": "el-tawil",
    "arabSea": "الطويل",
    "engTopic": "Short",
    "arabTopic": "قصائد قصيره",
    "poetId": 1805,
    "type": "عموديه",
    "order": 37,
    "link": "https://www.aldiwan.net/poem71288.html",
    "id": 74237
  },
  {
    "name": "كأن محجلات الدوم فيه",
    "quafia": "q-د",
    "engSea": "el-wafer",
    "arabSea": "الوافر",
    "engTopic": "Short",
    "arabTopic": "قصائد قصيره",
    "poetId": 1805,
    "type": "عموديه",
    "order": 38,
    "link": "https://www.aldiwan.net/poem71287.html",
    "id": 74238
  },
  {
    "name": "ملأت بقاع الأرض خيل جنوده",
    "quafia": "q-د",
    "engSea": "el-kamel",
    "arabSea": "الكامل",
    "engTopic": "Satire",
    "arabTopic": "قصائد هجاء",
    "poetId": 1805,
    "type": "عموديه",
    "order": 39,
    "link": "https://www.aldiwan.net/poem71286.html",
    "id": 74239
  },
  {
    "name": "قد اغتدي والليل في سواده",
    "quafia": "q-د",
    "engSea": "el-rijz",
    "arabSea": "الرجز",
    "engTopic": "Elegy",
    "arabTopic": "قصائد رثاء",
    "poetId": 1805,
    "type": "عموديه",
    "order": 40,
    "link": "https://www.aldiwan.net/poem71285.html",
    "id": 74240
  },
  {
    "name": "أضللت قلبي ورحت أنشده",
    "quafia": "q-د",
    "engSea": "el-monsareh",
    "arabSea": "المنسرح",
    "engTopic": "Short",
    "arabTopic": "قصائد قصيره",
    "poetId": 1805,
    "type": "عموديه",
    "order": 41,
    "link": "https://www.aldiwan.net/poem71284.html",
    "id": 74241
  },
  {
    "name": "على جسرة لا يدرك الطرف شأوها",
    "quafia": "q-ر",
    "engSea": "el-tawil",
    "arabSea": "الطويل",
    "engTopic": "Elegy",
    "arabTopic": "قصائد رثاء",
    "poetId": 1805,
    "type": "عموديه",
    "order": 42,
    "link": "https://www.aldiwan.net/poem71283.html",
    "id": 74242
  },
  {
    "name": "نجلي ببازي عيون ذوي النهى",
    "quafia": "q-ر",
    "engSea": "el-tawil",
    "arabSea": "الطويل",
    "engTopic": "Elegy",
    "arabTopic": "قصائد رثاء",
    "poetId": 1805,
    "type": "عموديه",
    "order": 43,
    "link": "https://www.aldiwan.net/poem71282.html",
    "id": 74243
  },
  {
    "name": "غدونا وطرف الليل وسنان غابر",
    "quafia": "q-ر",
    "engSea": "el-tawil",
    "arabSea": "الطويل",
    "engTopic": "Elegy",
    "arabTopic": "قصائد رثاء",
    "poetId": 1805,
    "type": "عموديه",
    "order": 44,
    "link": "https://www.aldiwan.net/poem71281.html",
    "id": 74244
  },
  {
    "name": "خبرت الأنام فما إن وجدت",
    "quafia": "q-ر",
    "engSea": "el-mota9areb",
    "arabSea": "المتقارب",
    "engTopic": "Elegy",
    "arabTopic": "قصائد رثاء",
    "poetId": 1805,
    "type": "عموديه",
    "order": 45,
    "link": "https://www.aldiwan.net/poem71280.html",
    "id": 74245
  },
  {
    "name": "أَخف القوانص جسما وروحا",
    "quafia": "q-ر",
    "engSea": "el-mota9areb",
    "arabSea": "المتقارب",
    "engTopic": "Elegy",
    "arabTopic": "قصائد رثاء",
    "poetId": 1805,
    "type": "عموديه",
    "order": 46,
    "link": "https://www.aldiwan.net/poem71279.html",
    "id": 74246
  },
  {
    "name": "سألت المنجم عن رحلة",
    "quafia": "q-ر",
    "engSea": "el-mota9areb",
    "arabSea": "المتقارب",
    "engTopic": "Elegy",
    "arabTopic": "قصائد رثاء",
    "poetId": 1805,
    "type": "عموديه",
    "order": 47,
    "link": "https://www.aldiwan.net/poem71278.html",
    "id": 74247
  },
  {
    "name": "أنعت صقرا يفترس الصقورا",
    "quafia": "q-ر",
    "engSea": "el-rijz",
    "arabSea": "الرجز",
    "engTopic": "Elegy",
    "arabTopic": "قصائد رثاء",
    "poetId": 1805,
    "type": "عموديه",
    "order": 48,
    "link": "https://www.aldiwan.net/poem71277.html",
    "id": 74248
  },
  {
    "name": "أقول كما قال الخليل بن أحمد",
    "quafia": "q-ر",
    "engSea": "el-tawil",
    "arabSea": "الطويل",
    "engTopic": "Praise",
    "arabTopic": "قصائد مدح",
    "poetId": 1805,
    "type": "عموديه",
    "order": 49,
    "link": "https://www.aldiwan.net/poem71276.html",
    "id": 74249
  },
  {
    "name": "تبلج بروح اليأس أو روحة الغنى",
    "quafia": "q-ر",
    "engSea": "el-tawil",
    "arabSea": "الطويل",
    "engTopic": "Elegy",
    "arabTopic": "قصائد رثاء",
    "poetId": 1805,
    "type": "عموديه",
    "order": 50,
    "link": "https://www.aldiwan.net/poem71275.html",
    "id": 74250
  },
  {
    "name": "خليلي هل للحزن مقلة عاشق",
    "quafia": "q-ي",
    "engSea": "el-tawil",
    "arabSea": "الطويل",
    "engTopic": "Romance",
    "arabTopic": "قصائد رومنسيه",
    "poetId": 1805,
    "type": "عموديه",
    "order": 51,
    "link": "https://www.aldiwan.net/poem71274.html",
    "id": 74251
  },
  {
    "name": "سل الليل عني كيف أرعى نجومه",
    "quafia": "q-ي",
    "engSea": "el-tawil",
    "arabSea": "الطويل",
    "engTopic": "Short",
    "arabTopic": "قصائد قصيره",
    "poetId": 1805,
    "type": "عموديه",
    "order": 52,
    "link": "https://www.aldiwan.net/poem71273.html",
    "id": 74252
  },
  {
    "name": "إنما الشعر ما تحصل من قبل",
    "quafia": "q-ر",
    "engSea": "el-khafif",
    "arabSea": "الخفيف",
    "engTopic": "Short",
    "arabTopic": "قصائد قصيره",
    "poetId": 1805,
    "type": "عموديه",
    "order": 53,
    "link": "https://www.aldiwan.net/poem71272.html",
    "id": 74253
  },
  {
    "name": "بكت للفراق وقد راعني",
    "quafia": "q-ر",
    "engSea": "el-mota9areb",
    "arabSea": "المتقارب",
    "engTopic": "Parting",
    "arabTopic": "قصائد فراق",
    "poetId": 1805,
    "type": "عموديه",
    "order": 54,
    "link": "https://www.aldiwan.net/poem71271.html",
    "id": 74254
  },
  {
    "name": "لأقتحمن الدهر مني بعزمة",
    "quafia": "q-ي",
    "engSea": "el-tawil",
    "arabSea": "الطويل",
    "engTopic": "Elegy",
    "arabTopic": "قصائد رثاء",
    "poetId": 1805,
    "type": "عموديه",
    "order": 55,
    "link": "https://www.aldiwan.net/poem71270.html",
    "id": 74255
  },
  {
    "name": "يا ديار االأحباب هل من مجيب",
    "quafia": "q-ر",
    "engSea": "el-khafif",
    "arabSea": "الخفيف",
    "engTopic": "Elegy",
    "arabTopic": "قصائد رثاء",
    "poetId": 1805,
    "type": "عموديه",
    "order": 56,
    "link": "https://www.aldiwan.net/poem71269.html",
    "id": 74256
  },
  {
    "name": "قلت لها لا تكثري",
    "quafia": "q-ي",
    "engSea": "majzoua-el-rijz",
    "arabSea": "مجزوء الرجز",
    "engTopic": "Romance",
    "arabTopic": "قصائد رومنسيه",
    "poetId": 1805,
    "type": "عموديه",
    "order": 57,
    "link": "https://www.aldiwan.net/poem71268.html",
    "id": 74257
  },
  {
    "name": "ولما توافقنا غداة وداعنا",
    "quafia": "q-ر",
    "engSea": "el-tawil",
    "arabSea": "الطويل",
    "engTopic": "Satire",
    "arabTopic": "قصائد هجاء",
    "poetId": 1805,
    "type": "عموديه",
    "order": 58,
    "link": "https://www.aldiwan.net/poem71267.html",
    "id": 74258
  },
  {
    "name": "يا قائص أغد علينا",
    "quafia": "q-ر",
    "engSea": "el-mojateth",
    "arabSea": "المجتث",
    "engTopic": "Elegy",
    "arabTopic": "قصائد رثاء",
    "poetId": 1805,
    "type": "عموديه",
    "order": 59,
    "link": "https://www.aldiwan.net/poem71266.html",
    "id": 74259
  },
  {
    "name": "رب عاري الظهر منعفر",
    "quafia": "q-ر",
    "engSea": "el-madid",
    "arabSea": "المديد",
    "engTopic": "Elegy",
    "arabTopic": "قصائد رثاء",
    "poetId": 1805,
    "type": "عموديه",
    "order": 60,
    "link": "https://www.aldiwan.net/poem71265.html",
    "id": 74260
  },
  {
    "name": "انتزع يا صاح بازينا",
    "quafia": "q-ر",
    "engSea": "el-madid",
    "arabSea": "المديد",
    "engTopic": "Satire",
    "arabTopic": "قصائد هجاء",
    "poetId": 1805,
    "type": "عموديه",
    "order": 61,
    "link": "https://www.aldiwan.net/poem71264.html",
    "id": 74261
  },
  {
    "name": "لما أجال الفجر في أستاره",
    "quafia": "q-ر",
    "engSea": "el-rijz",
    "arabSea": "الرجز",
    "engTopic": "Elegy",
    "arabTopic": "قصائد رثاء",
    "poetId": 1805,
    "type": "عموديه",
    "order": 62,
    "link": "https://www.aldiwan.net/poem71263.html",
    "id": 74262
  },
  {
    "name": "لو أن حيا واثقا لعمره",
    "quafia": "q-ر",
    "engSea": "el-rijz",
    "arabSea": "الرجز",
    "engTopic": "Elegy",
    "arabTopic": "قصائد رثاء",
    "poetId": 1805,
    "type": "عموديه",
    "order": 63,
    "link": "https://www.aldiwan.net/poem71262.html",
    "id": 74263
  },
  {
    "name": "أنعت صقرا جل باريه وعز",
    "quafia": "q-ز",
    "engSea": "el-rijz",
    "arabSea": "الرجز",
    "engTopic": "Praise",
    "arabTopic": "قصائد مدح",
    "poetId": 1805,
    "type": "عموديه",
    "order": 64,
    "link": "https://www.aldiwan.net/poem71261.html",
    "id": 74264
  },
  {
    "name": "وإني لأنسى السر كي لا أذيعه",
    "quafia": "q-س",
    "engSea": "el-tawil",
    "arabSea": "الطويل",
    "engTopic": "Satire",
    "arabTopic": "قصائد هجاء",
    "poetId": 1805,
    "type": "عموديه",
    "order": 65,
    "link": "https://www.aldiwan.net/poem71260.html",
    "id": 74265
  },
  {
    "name": "آثاره تحمي البقاع وزأره",
    "quafia": "q-س",
    "engSea": "el-kamel",
    "arabSea": "الكامل",
    "engTopic": "Satire",
    "arabTopic": "قصائد هجاء",
    "poetId": 1805,
    "type": "عموديه",
    "order": 66,
    "link": "https://www.aldiwan.net/poem71259.html",
    "id": 74266
  },
  {
    "name": "لا عيش إلا بكف جارية",
    "quafia": "q-ض",
    "engSea": "el-monsareh",
    "arabSea": "المنسرح",
    "engTopic": "Romance",
    "arabTopic": "قصائد رومنسيه",
    "poetId": 1805,
    "type": "عموديه",
    "order": 67,
    "link": "https://www.aldiwan.net/poem71258.html",
    "id": 74267
  },
  {
    "name": "ليس شيء أحر في مهجة العاشق",
    "quafia": "q-ض",
    "engSea": "el-khafif",
    "arabSea": "الخفيف",
    "engTopic": "Romance",
    "arabTopic": "قصائد رومنسيه",
    "poetId": 1805,
    "type": "عموديه",
    "order": 68,
    "link": "https://www.aldiwan.net/poem71257.html",
    "id": 74268
  },
  {
    "name": "مثل دعاء مستجاب إن علا",
    "quafia": "q-ط",
    "engSea": "el-rijz",
    "arabSea": "الرجز",
    "engTopic": "Short",
    "arabTopic": "قصائد قصيره",
    "poetId": 1805,
    "type": "عموديه",
    "order": 69,
    "link": "https://www.aldiwan.net/poem71256.html",
    "id": 74269
  },
  {
    "name": "يا رب ضحضاح قريب المشرع",
    "quafia": "q-ع",
    "engSea": "el-rijz",
    "arabSea": "الرجز",
    "engTopic": "Short",
    "arabTopic": "قصائد قصيره",
    "poetId": 1805,
    "type": "عموديه",
    "order": 70,
    "link": "https://www.aldiwan.net/poem71255.html",
    "id": 74270
  },
  {
    "name": "يا صاح جد بدستبان أفرع",
    "quafia": "q-ع",
    "engSea": "el-rijz",
    "arabSea": "الرجز",
    "engTopic": "Satire",
    "arabTopic": "قصائد هجاء",
    "poetId": 1805,
    "type": "عموديه",
    "order": 71,
    "link": "https://www.aldiwan.net/poem71254.html",
    "id": 74271
  },
  {
    "name": "هواي وعقلي فيك ضدان لم يزل",
    "quafia": "q-ف",
    "engSea": "el-tawil",
    "arabSea": "الطويل",
    "engTopic": "Short",
    "arabTopic": "قصائد قصيره",
    "poetId": 1805,
    "type": "عموديه",
    "order": 72,
    "link": "https://www.aldiwan.net/poem71253.html",
    "id": 74272
  },
  {
    "name": "أشدد يديك بمن تهوى فما أحد",
    "quafia": "q-ف",
    "engSea": "bassit",
    "arabSea": "البسيط",
    "engTopic": "Short",
    "arabTopic": "قصائد قصيره",
    "poetId": 1805,
    "type": "عموديه",
    "order": 73,
    "link": "https://www.aldiwan.net/poem71252.html",
    "id": 74273
  },
  {
    "name": "وإذا بصرت بكفها اليسرى حكت",
    "quafia": "q-ف",
    "engSea": "el-kamel",
    "arabSea": "الكامل",
    "engTopic": "Satire",
    "arabTopic": "قصائد هجاء",
    "poetId": 1805,
    "type": "عموديه",
    "order": 74,
    "link": "https://www.aldiwan.net/poem71251.html",
    "id": 74274
  },
  {
    "name": "وشادن ما توخى وصفه أحد",
    "quafia": "q-ف",
    "engSea": "bassit",
    "arabSea": "البسيط",
    "engTopic": "Short",
    "arabTopic": "قصائد قصيره",
    "poetId": 1805,
    "type": "عموديه",
    "order": 75,
    "link": "https://www.aldiwan.net/poem71250.html",
    "id": 74275
  },
  {
    "name": "لفظي ولفظك بالشكوى قد ائتلفا",
    "quafia": "q-ف",
    "engSea": "bassit",
    "arabSea": "البسيط",
    "engTopic": "Short",
    "arabTopic": "قصائد قصيره",
    "poetId": 1805,
    "type": "عموديه",
    "order": 76,
    "link": "https://www.aldiwan.net/poem71249.html",
    "id": 74276
  },
  {
    "name": "إِن أَنت لم تحدث إلي يدا",
    "quafia": "q-ف",
    "engSea": "ahd-el-kamel",
    "arabSea": "أحذ الكامل",
    "engTopic": "Satire",
    "arabTopic": "قصائد هجاء",
    "poetId": 1805,
    "type": "عموديه",
    "order": 77,
    "link": "https://www.aldiwan.net/poem71248.html",
    "id": 74277
  },
  {
    "name": "وضيئلة تختال في حركاتها",
    "quafia": "q-ي",
    "engSea": "el-kamel",
    "arabSea": "الكامل",
    "engTopic": "Satire",
    "arabTopic": "قصائد هجاء",
    "poetId": 1805,
    "type": "عموديه",
    "order": 78,
    "link": "https://www.aldiwan.net/poem71247.html",
    "id": 74278
  },
  {
    "name": "يتحير الشعراء إن سمعوا به",
    "quafia": "q-ف",
    "engSea": "el-kamel",
    "arabSea": "الكامل",
    "engTopic": "Satire",
    "arabTopic": "قصائد هجاء",
    "poetId": 1805,
    "type": "عموديه",
    "order": 79,
    "link": "https://www.aldiwan.net/poem71246.html",
    "id": 74279
  },
  {
    "name": "قبلته خلسة من عين راقبه",
    "quafia": "q-ف",
    "engSea": "bassit",
    "arabSea": "البسيط",
    "engTopic": "Romance",
    "arabTopic": "قصائد رومنسيه",
    "poetId": 1805,
    "type": "عموديه",
    "order": 80,
    "link": "https://www.aldiwan.net/poem71245.html",
    "id": 74280
  },
  {
    "name": "سل الليل عن ما قد لقيت وما ألقى",
    "quafia": "q-ق",
    "engSea": "el-tawil",
    "arabSea": "الطويل",
    "engTopic": "Short",
    "arabTopic": "قصائد قصيره",
    "poetId": 1805,
    "type": "عموديه",
    "order": 81,
    "link": "https://www.aldiwan.net/poem71244.html",
    "id": 74281
  },
  {
    "name": "أنعت صقرا كرزا بطريقا",
    "quafia": "q-ق",
    "engSea": "el-rijz",
    "arabSea": "الرجز",
    "engTopic": "Satire",
    "arabTopic": "قصائد هجاء",
    "poetId": 1805,
    "type": "عموديه",
    "order": 82,
    "link": "https://www.aldiwan.net/poem71243.html",
    "id": 74282
  },
  {
    "name": "قنصت من هضبة زرقا",
    "quafia": "q-ق",
    "engSea": "el-mota9areb",
    "arabSea": "المتقارب",
    "engTopic": "Elegy",
    "arabTopic": "قصائد رثاء",
    "poetId": 1805,
    "type": "عموديه",
    "order": 83,
    "link": "https://www.aldiwan.net/poem71242.html",
    "id": 74283
  },
  {
    "name": "ومورد يجذل عين الرامق",
    "quafia": "q-ق",
    "engSea": "el-rijz",
    "arabSea": "الرجز",
    "engTopic": "Elegy",
    "arabTopic": "قصائد رثاء",
    "poetId": 1805,
    "type": "عموديه",
    "order": 84,
    "link": "https://www.aldiwan.net/poem71241.html",
    "id": 74284
  },
  {
    "name": "ولست معاتبا خلا لأني",
    "quafia": "q-ق",
    "engSea": "el-wafer",
    "arabSea": "الوافر",
    "engTopic": "Elegy",
    "arabTopic": "قصائد رثاء",
    "poetId": 1805,
    "type": "عموديه",
    "order": 85,
    "link": "https://www.aldiwan.net/poem71240.html",
    "id": 74285
  },
  {
    "name": "عدمت من الحبيبة رجع كف",
    "quafia": "q-ق",
    "engSea": "el-wafer",
    "arabSea": "الوافر",
    "engTopic": "Satire",
    "arabTopic": "قصائد هجاء",
    "poetId": 1805,
    "type": "عموديه",
    "order": 86,
    "link": "https://www.aldiwan.net/poem71239.html",
    "id": 74286
  },
  {
    "name": "هل لك يا ابن القانص البطريق",
    "quafia": "q-ق",
    "engSea": "el-rijz",
    "arabSea": "الرجز",
    "engTopic": "Satire",
    "arabTopic": "قصائد هجاء",
    "poetId": 1805,
    "type": "عموديه",
    "order": 87,
    "link": "https://www.aldiwan.net/poem71238.html",
    "id": 74287
  },
  {
    "name": "يا رب كلب ربه في رزقه",
    "quafia": "q-ق",
    "engSea": "el-rijz",
    "arabSea": "الرجز",
    "engTopic": "General",
    "arabTopic": "قصائد عامه",
    "poetId": 1805,
    "type": "عموديه",
    "order": 88,
    "link": "https://www.aldiwan.net/poem71237.html",
    "id": 74288
  },
  {
    "name": "أحوى عليه مسائح من ليطة",
    "quafia": "q-ق",
    "engSea": "el-kamel",
    "arabSea": "الكامل",
    "engTopic": "Satire",
    "arabTopic": "قصائد هجاء",
    "poetId": 1805,
    "type": "عموديه",
    "order": 89,
    "link": "https://www.aldiwan.net/poem71236.html",
    "id": 74289
  },
  {
    "name": "لم يعتصم ذو مهرب بفراقه",
    "quafia": "q-ق",
    "engSea": "el-kamel",
    "arabSea": "الكامل",
    "engTopic": "Short",
    "arabTopic": "قصائد قصيره",
    "poetId": 1805,
    "type": "عموديه",
    "order": 90,
    "link": "https://www.aldiwan.net/poem71235.html",
    "id": 74290
  },
  {
    "name": "كالبدر في إشراقه",
    "quafia": "q-ق",
    "engSea": "el-rijz",
    "arabSea": "الرجز",
    "engTopic": "Short",
    "arabTopic": "قصائد قصيره",
    "poetId": 1805,
    "type": "عموديه",
    "order": 91,
    "link": "https://www.aldiwan.net/poem71234.html",
    "id": 74291
  },
  {
    "name": "فديتك لو أنهم أنصفوا",
    "quafia": "q-ك",
    "engSea": "el-mota9areb",
    "arabSea": "المتقارب",
    "engTopic": "Romance",
    "arabTopic": "قصائد رومنسيه",
    "poetId": 1805,
    "type": "عموديه",
    "order": 92,
    "link": "https://www.aldiwan.net/poem71233.html",
    "id": 74292
  },
  {
    "name": "القصد شيء كل ما دونه",
    "quafia": "q-ل",
    "engSea": "el-sari3",
    "arabSea": "السريع",
    "engTopic": "Satire",
    "arabTopic": "قصائد هجاء",
    "poetId": 1805,
    "type": "عموديه",
    "order": 93,
    "link": "https://www.aldiwan.net/poem71232.html",
    "id": 74293
  },
  {
    "name": "هم للعداة كآجال مسومة",
    "quafia": "q-ل",
    "engSea": "bassit",
    "arabSea": "البسيط",
    "engTopic": "General",
    "arabTopic": "قصائد عامه",
    "poetId": 1805,
    "type": "عموديه",
    "order": 94,
    "link": "https://www.aldiwan.net/poem71231.html",
    "id": 74294
  },
  {
    "name": "زعمت أبا سهل بأنك جامع",
    "quafia": "q-ل",
    "engSea": "el-tawil",
    "arabSea": "الطويل",
    "engTopic": "Condemnation",
    "arabTopic": "قصائد ذم",
    "poetId": 1805,
    "type": "عموديه",
    "order": 95,
    "link": "https://www.aldiwan.net/poem71230.html",
    "id": 74295
  },
  {
    "name": "تأمل بعينك هذا الأنام",
    "quafia": "q-ل",
    "engSea": "el-mota9areb",
    "arabSea": "المتقارب",
    "engTopic": "Satire",
    "arabTopic": "قصائد هجاء",
    "poetId": 1805,
    "type": "عموديه",
    "order": 96,
    "link": "https://www.aldiwan.net/poem71229.html",
    "id": 74296
  },
  {
    "name": "ويهماء تسقط عنها الظنون",
    "quafia": "q-ل",
    "engSea": "el-mota9areb",
    "arabSea": "المتقارب",
    "engTopic": "Elegy",
    "arabTopic": "قصائد رثاء",
    "poetId": 1805,
    "type": "عموديه",
    "order": 97,
    "link": "https://www.aldiwan.net/poem71228.html",
    "id": 74297
  },
  {
    "name": "يهياه لا تبرحا ثعالا",
    "quafia": "q-ل",
    "engSea": "el-rijz",
    "arabSea": "الرجز",
    "engTopic": "Satire",
    "arabTopic": "قصائد هجاء",
    "poetId": 1805,
    "type": "عموديه",
    "order": 98,
    "link": "https://www.aldiwan.net/poem71227.html",
    "id": 74298
  },
  {
    "name": "لو كما تجهل تدري",
    "quafia": "q-ل",
    "engSea": "majzoua-el-ramel",
    "arabSea": "مجزوء الرمل",
    "engTopic": "Short",
    "arabTopic": "قصائد قصيره",
    "poetId": 1805,
    "type": "عموديه",
    "order": 99,
    "link": "https://www.aldiwan.net/poem71226.html",
    "id": 74299
  },
  {
    "name": "وقلة طود مشمخر شعافه",
    "quafia": "q-ل",
    "engSea": "el-tawil",
    "arabSea": "الطويل",
    "engTopic": "Elegy",
    "arabTopic": "قصائد رثاء",
    "poetId": 1805,
    "type": "عموديه",
    "order": 100,
    "link": "https://www.aldiwan.net/poem71225.html",
    "id": 74300
  },
  {
    "name": "نغدو بصقر كرز مؤهل",
    "quafia": "q-ل",
    "engSea": "el-rijz",
    "arabSea": "الرجز",
    "engTopic": "Praise",
    "arabTopic": "قصائد مدح",
    "poetId": 1805,
    "type": "عموديه",
    "order": 101,
    "link": "https://www.aldiwan.net/poem71224.html",
    "id": 74301
  },
  {
    "name": "لا صيد إلا صيد باز أبجل",
    "quafia": "q-ل",
    "engSea": "el-rijz",
    "arabSea": "الرجز",
    "engTopic": "Praise",
    "arabTopic": "قصائد مدح",
    "poetId": 1805,
    "type": "عموديه",
    "order": 102,
    "link": "https://www.aldiwan.net/poem71223.html",
    "id": 74302
  },
  {
    "name": "وليت قضاء ولم تعدل",
    "quafia": "q-ل",
    "engSea": "el-mota9areb",
    "arabSea": "المتقارب",
    "engTopic": "Romance",
    "arabTopic": "قصائد رومنسيه",
    "poetId": 1805,
    "type": "عموديه",
    "order": 103,
    "link": "https://www.aldiwan.net/poem71222.html",
    "id": 74303
  },
  {
    "name": "كلام يخوض غمار البحار",
    "quafia": "q-ل",
    "engSea": "el-mota9areb",
    "arabSea": "المتقارب",
    "engTopic": "Praise",
    "arabTopic": "قصائد مدح",
    "poetId": 1805,
    "type": "عموديه",
    "order": 104,
    "link": "https://www.aldiwan.net/poem71221.html",
    "id": 74304
  },
  {
    "name": "كأنه الدهر في إدراك غابته",
    "quafia": "q-ل",
    "engSea": "bassit",
    "arabSea": "البسيط",
    "engTopic": "Short",
    "arabTopic": "قصائد قصيره",
    "poetId": 1805,
    "type": "عموديه",
    "order": 105,
    "link": "https://www.aldiwan.net/poem71220.html",
    "id": 74305
  },
  {
    "name": "إذا كان دوني من بليت بجهله",
    "quafia": "q-ل",
    "engSea": "el-tawil",
    "arabSea": "الطويل",
    "engTopic": "Elegy",
    "arabTopic": "قصائد رثاء",
    "poetId": 1805,
    "type": "عموديه",
    "order": 106,
    "link": "https://www.aldiwan.net/poem71219.html",
    "id": 74306
  },
  {
    "name": "ونحن أناس يعرف الناس فضلنا",
    "quafia": "q-ل",
    "engSea": "el-tawil",
    "arabSea": "الطويل",
    "engTopic": "Praise",
    "arabTopic": "قصائد مدح",
    "poetId": 1805,
    "type": "عموديه",
    "order": 107,
    "link": "https://www.aldiwan.net/poem71218.html",
    "id": 74307
  },
  {
    "name": "فلحمي وما قد سيط باللحم من دمي",
    "quafia": "q-ي",
    "engSea": "el-tawil",
    "arabSea": "الطويل",
    "engTopic": "Satire",
    "arabTopic": "قصائد هجاء",
    "poetId": 1805,
    "type": "عموديه",
    "order": 108,
    "link": "https://www.aldiwan.net/poem71217.html",
    "id": 74308
  },
  {
    "name": "ولي أمل بعيد لست أثني",
    "quafia": "q-ي",
    "engSea": "el-wafer",
    "arabSea": "الوافر",
    "engTopic": "Short",
    "arabTopic": "قصائد قصيره",
    "poetId": 1805,
    "type": "عموديه",
    "order": 109,
    "link": "https://www.aldiwan.net/poem71216.html",
    "id": 74309
  },
  {
    "name": "لما عطفن رءوسهنن",
    "quafia": "q-ل",
    "engSea": "majzoua-el-kamel",
    "arabSea": "مجزوء الكامل",
    "engTopic": "Short",
    "arabTopic": "قصائد قصيره",
    "poetId": 1805,
    "type": "عموديه",
    "order": 110,
    "link": "https://www.aldiwan.net/poem71215.html",
    "id": 74310
  },
  {
    "name": "رأيت على أكوارنا كل ماجد",
    "quafia": "q-م",
    "engSea": "el-tawil",
    "arabSea": "الطويل",
    "engTopic": "Satire",
    "arabTopic": "قصائد هجاء",
    "poetId": 1805,
    "type": "عموديه",
    "order": 111,
    "link": "https://www.aldiwan.net/poem71214.html",
    "id": 74311
  },
  {
    "name": "وأنمر موشي القميص مولع",
    "quafia": "q-م",
    "engSea": "el-tawil",
    "arabSea": "الطويل",
    "engTopic": "Satire",
    "arabTopic": "قصائد هجاء",
    "poetId": 1805,
    "type": "عموديه",
    "order": 112,
    "link": "https://www.aldiwan.net/poem71213.html",
    "id": 74312
  },
  {
    "name": "إن كنت بالذل راضيا فأرح",
    "quafia": "q-م",
    "engSea": "bassit",
    "arabSea": "البسيط",
    "engTopic": "Elegy",
    "arabTopic": "قصائد رثاء",
    "poetId": 1805,
    "type": "عموديه",
    "order": 113,
    "link": "https://www.aldiwan.net/poem71212.html",
    "id": 74313
  },
  {
    "name": "سمعنا بالصديق ولا نراه",
    "quafia": "q-م",
    "engSea": "el-wafer",
    "arabSea": "الوافر",
    "engTopic": "Short",
    "arabTopic": "قصائد قصيره",
    "poetId": 1805,
    "type": "عموديه",
    "order": 114,
    "link": "https://www.aldiwan.net/poem71211.html",
    "id": 74314
  },
  {
    "name": "لم تبن في الدنيا سماء مكارم",
    "quafia": "q-م",
    "engSea": "el-kamel",
    "arabSea": "الكامل",
    "engTopic": "Romance",
    "arabTopic": "قصائد رومنسيه",
    "poetId": 1805,
    "type": "عموديه",
    "order": 115,
    "link": "https://www.aldiwan.net/poem71210.html",
    "id": 74315
  },
  {
    "name": "أهوى مقاربة العذول لأنه",
    "quafia": "q-م",
    "engSea": "el-kamel",
    "arabSea": "الكامل",
    "engTopic": "Short",
    "arabTopic": "قصائد قصيره",
    "poetId": 1805,
    "type": "عموديه",
    "order": 116,
    "link": "https://www.aldiwan.net/poem71209.html",
    "id": 74316
  },
  {
    "name": "رب ذي شبلين قسورة",
    "quafia": "q-م",
    "engSea": "el-madid",
    "arabSea": "المديد",
    "engTopic": "Satire",
    "arabTopic": "قصائد هجاء",
    "poetId": 1805,
    "type": "عموديه",
    "order": 117,
    "link": "https://www.aldiwan.net/poem71208.html",
    "id": 74317
  },
  {
    "name": "لم أسل عنك ولم أخنك ولم يكن",
    "quafia": "q-ن",
    "engSea": "el-kamel",
    "arabSea": "الكامل",
    "engTopic": "Romance",
    "arabTopic": "قصائد رومنسيه",
    "poetId": 1805,
    "type": "عموديه",
    "order": 118,
    "link": "https://www.aldiwan.net/poem71207.html",
    "id": 74318
  },
  {
    "name": "كتبت إليكم اشتكي حرقة الهوى",
    "quafia": "q-ن",
    "engSea": "el-tawil",
    "arabSea": "الطويل",
    "engTopic": "Elegy",
    "arabTopic": "قصائد رثاء",
    "poetId": 1805,
    "type": "عموديه",
    "order": 119,
    "link": "https://www.aldiwan.net/poem71206.html",
    "id": 74319
  },
  {
    "name": "وجود الغنى أن لا تكاثر في الغنى",
    "quafia": "q-ن",
    "engSea": "el-tawil",
    "arabSea": "الطويل",
    "engTopic": "Short",
    "arabTopic": "قصائد قصيره",
    "poetId": 1805,
    "type": "عموديه",
    "order": 120,
    "link": "https://www.aldiwan.net/poem71205.html",
    "id": 74320
  },
  {
    "name": "لعن الله صنعة الشعر ماذا",
    "quafia": "q-ن",
    "engSea": "el-khafif",
    "arabSea": "الخفيف",
    "engTopic": "Elegy",
    "arabTopic": "قصائد رثاء",
    "poetId": 1805,
    "type": "عموديه",
    "order": 121,
    "link": "https://www.aldiwan.net/poem71204.html",
    "id": 74321
  },
  {
    "name": "لنا قينة ترنو بناظرتين",
    "quafia": "q-ن",
    "engSea": "el-tawil",
    "arabSea": "الطويل",
    "engTopic": "Short",
    "arabTopic": "قصائد قصيره",
    "poetId": 1805,
    "type": "عموديه",
    "order": 122,
    "link": "https://www.aldiwan.net/poem71203.html",
    "id": 74322
  },
  {
    "name": "قضب الزبرجد قد حملن شقائقا",
    "quafia": "q-ن",
    "engSea": "el-kamel",
    "arabSea": "الكامل",
    "engTopic": "Elegy",
    "arabTopic": "قصائد رثاء",
    "poetId": 1805,
    "type": "عموديه",
    "order": 123,
    "link": "https://www.aldiwan.net/poem71202.html",
    "id": 74323
  },
  {
    "name": "هل لك يا قناص في شاهين",
    "quafia": "q-ن",
    "engSea": "el-rijz",
    "arabSea": "الرجز",
    "engTopic": "Satire",
    "arabTopic": "قصائد هجاء",
    "poetId": 1805,
    "type": "عموديه",
    "order": 124,
    "link": "https://www.aldiwan.net/poem71201.html",
    "id": 74324
  },
  {
    "name": "أيا صاح بازي إنه",
    "quafia": "q-ن",
    "engSea": "el-mota9areb",
    "arabSea": "المتقارب",
    "engTopic": "Elegy",
    "arabTopic": "قصائد رثاء",
    "poetId": 1805,
    "type": "عموديه",
    "order": 125,
    "link": "https://www.aldiwan.net/poem71200.html",
    "id": 74325
  },
  {
    "name": "وعفرناة ضبارمة",
    "quafia": "q-ن",
    "engSea": "el-madid",
    "arabSea": "المديد",
    "engTopic": "Satire",
    "arabTopic": "قصائد هجاء",
    "poetId": 1805,
    "type": "عموديه",
    "order": 126,
    "link": "https://www.aldiwan.net/poem71199.html",
    "id": 74326
  },
  {
    "name": "الشعر ما قومت زيغ صدوره",
    "quafia": "q-ن",
    "engSea": "el-kamel",
    "arabSea": "الكامل",
    "engTopic": "Elegy",
    "arabTopic": "قصائد رثاء",
    "poetId": 1805,
    "type": "عموديه",
    "order": 127,
    "link": "https://www.aldiwan.net/poem71198.html",
    "id": 74327
  },
  {
    "name": "ملوك ساسان على كأسها",
    "quafia": "q-ن",
    "engSea": "bassit",
    "arabSea": "البسيط",
    "engTopic": "Short",
    "arabTopic": "قصائد قصيره",
    "poetId": 1805,
    "type": "عموديه",
    "order": 128,
    "link": "https://www.aldiwan.net/poem71197.html",
    "id": 74328
  },
  {
    "name": "إنما مجلس الندامى بساط",
    "quafia": "q-و",
    "engSea": "el-khafif",
    "arabSea": "الخفيف",
    "engTopic": "Short",
    "arabTopic": "قصائد قصيره",
    "poetId": 1805,
    "type": "عموديه",
    "order": 129,
    "link": "https://www.aldiwan.net/poem71196.html",
    "id": 74329
  },
  {
    "name": "ما في البرية أخزى عند فاطرها",
    "quafia": "q-ي",
    "engSea": "bassit",
    "arabSea": "البسيط",
    "engTopic": "Short",
    "arabTopic": "قصائد قصيره",
    "poetId": 1805,
    "type": "عموديه",
    "order": 130,
    "link": "https://www.aldiwan.net/poem71195.html",
    "id": 74330
  },
  {
    "name": "لو كان لله شبه من خليقته",
    "quafia": "q-ي",
    "engSea": "bassit",
    "arabSea": "البسيط",
    "engTopic": "Religious",
    "arabTopic": "قصائد دينية",
    "poetId": 1805,
    "type": "عموديه",
    "order": 131,
    "link": "https://www.aldiwan.net/poem71194.html",
    "id": 74331
  },
  {
    "name": "من تحلى بغير ما هو فيه",
    "quafia": "q-ي",
    "engSea": "el-khafif",
    "arabSea": "الخفيف",
    "engTopic": "Short",
    "arabTopic": "قصائد قصيره",
    "poetId": 1805,
    "type": "عموديه",
    "order": 132,
    "link": "https://www.aldiwan.net/poem71193.html",
    "id": 74332
  },
  {
    "name": "قد أغتدي وعيون الفجر واسنة",
    "quafia": "q-ي",
    "engSea": "bassit",
    "arabSea": "البسيط",
    "engTopic": "Praise",
    "arabTopic": "قصائد مدح",
    "poetId": 1805,
    "type": "عموديه",
    "order": 133,
    "link": "https://www.aldiwan.net/poem71192.html",
    "id": 74333
  },
  {
    "name": "يا ربما كأس تناولتها",
    "quafia": "q-ي",
    "engSea": "el-sari3",
    "arabSea": "السريع",
    "engTopic": "Elegy",
    "arabTopic": "قصائد رثاء",
    "poetId": 1805,
    "type": "عموديه",
    "order": 134,
    "link": "https://www.aldiwan.net/poem71191.html",
    "id": 74334
  },
  {
    "name": "كأنما الآل باعوا لها",
    "quafia": "q-ي",
    "engSea": "el-sari3",
    "arabSea": "السريع",
    "engTopic": "General",
    "arabTopic": "قصائد عامه",
    "poetId": 1805,
    "type": "عموديه",
    "order": 135,
    "link": "https://www.aldiwan.net/poem71190.html",
    "id": 74335
  },
  {
    "name": "إذا هم هما لم ير الليل غمة",
    "quafia": "q-ب",
    "engSea": "el-tawil",
    "arabSea": "الطويل",
    "engTopic": "Satire",
    "arabTopic": "قصائد هجاء",
    "poetId": 1806,
    "type": "عموديه",
    "order": 1,
    "link": "https://www.aldiwan.net/poem71189.html",
    "id": 74336
  },
  {
    "name": "عفت أجلى من أهلها فقليبها",
    "quafia": "q-ب",
    "engSea": "el-tawil",
    "arabSea": "الطويل",
    "engTopic": "Romance",
    "arabTopic": "قصائد رومنسيه",
    "poetId": 1806,
    "type": "عموديه",
    "order": 2,
    "link": "https://www.aldiwan.net/poem71188.html",
    "id": 74337
  },
  {
    "name": "إني لعمر أبيهم لا أصالحهم",
    "quafia": "q-ب",
    "engSea": "bassit",
    "arabSea": "البسيط",
    "engTopic": "Short",
    "arabTopic": "قصائد قصيره",
    "poetId": 1806,
    "type": "عموديه",
    "order": 3,
    "link": "https://www.aldiwan.net/poem71187.html",
    "id": 74338
  },
  {
    "name": "عفت فردة من أهلها فجنابها",
    "quafia": "q-ب",
    "engSea": "el-tawil",
    "arabSea": "الطويل",
    "engTopic": "Satire",
    "arabTopic": "قصائد هجاء",
    "poetId": 1806,
    "type": "عموديه",
    "order": 4,
    "link": "https://www.aldiwan.net/poem71186.html",
    "id": 74339
  },
  {
    "name": "تذكر ذكرى من قطاة فأنصبا",
    "quafia": "q-ب",
    "engSea": "el-tawil",
    "arabSea": "الطويل",
    "engTopic": "Praise",
    "arabTopic": "قصائد مدح",
    "poetId": 1806,
    "type": "عموديه",
    "order": 5,
    "link": "https://www.aldiwan.net/poem71185.html",
    "id": 74340
  },
  {
    "name": "ألا هل أتى فتيان قومي أنني",
    "quafia": "q-ب",
    "engSea": "el-tawil",
    "arabSea": "الطويل",
    "engTopic": "Satire",
    "arabTopic": "قصائد هجاء",
    "poetId": 1806,
    "type": "عموديه",
    "order": 6,
    "link": "https://www.aldiwan.net/poem71184.html",
    "id": 74341
  },
  {
    "name": "هل من معاشر غيركم أدعوهم",
    "quafia": "q-ب",
    "engSea": "el-kamel",
    "arabSea": "الكامل",
    "engTopic": "Condemnation",
    "arabTopic": "قصائد ذم",
    "poetId": 1806,
    "type": "عموديه",
    "order": 7,
    "link": "https://www.aldiwan.net/poem71183.html",
    "id": 74342
  },
  {
    "name": "أنا إبن الأكرمين بني قشير",
    "quafia": "q-ب",
    "engSea": "el-wafer",
    "arabSea": "الوافر",
    "engTopic": "Condemnation",
    "arabTopic": "قصائد ذم",
    "poetId": 1806,
    "type": "عموديه",
    "order": 8,
    "link": "https://www.aldiwan.net/poem71182.html",
    "id": 74343
  },
  {
    "name": "أتتك المنايا من بلاد بعيدة",
    "quafia": "q-ب",
    "engSea": "el-tawil",
    "arabSea": "الطويل",
    "engTopic": "Satire",
    "arabTopic": "قصائد هجاء",
    "poetId": 1806,
    "type": "عموديه",
    "order": 9,
    "link": "https://www.aldiwan.net/poem71181.html",
    "id": 74344
  },
  {
    "name": "عفا لفلف من أهله فالمضيح",
    "quafia": "q-ح",
    "engSea": "el-tawil",
    "arabSea": "الطويل",
    "engTopic": "Satire",
    "arabTopic": "قصائد هجاء",
    "poetId": 1806,
    "type": "عموديه",
    "order": 10,
    "link": "https://www.aldiwan.net/poem71180.html",
    "id": 74345
  },
  {
    "name": "صرمت شميلة وجهة فتجلد",
    "quafia": "q-د",
    "engSea": "el-tawil",
    "arabSea": "الطويل",
    "engTopic": "Satire",
    "arabTopic": "قصائد هجاء",
    "poetId": 1806,
    "type": "عموديه",
    "order": 11,
    "link": "https://www.aldiwan.net/poem71179.html",
    "id": 74346
  },
  {
    "name": "جزى الله عنا والجزاء بكفه",
    "quafia": "q-د",
    "engSea": "el-tawil",
    "arabSea": "الطويل",
    "engTopic": "Praise",
    "arabTopic": "قصائد مدح",
    "poetId": 1806,
    "type": "عموديه",
    "order": 12,
    "link": "https://www.aldiwan.net/poem71178.html",
    "id": 74347
  },
  {
    "name": "يابنت جون أبانت بنت شداد",
    "quafia": "q-د",
    "engSea": "bassit",
    "arabSea": "البسيط",
    "engTopic": "Romance",
    "arabTopic": "قصائد رومنسيه",
    "poetId": 1806,
    "type": "عموديه",
    "order": 13,
    "link": "https://www.aldiwan.net/poem71177.html",
    "id": 74348
  },
  {
    "name": "ولما أن رأيت بني حصين",
    "quafia": "q-د",
    "engSea": "el-wafer",
    "arabSea": "الوافر",
    "engTopic": "Reproach",
    "arabTopic": "قصائد عتاب",
    "poetId": 1806,
    "type": "عموديه",
    "order": 14,
    "link": "https://www.aldiwan.net/poem71176.html",
    "id": 74349
  },
  {
    "name": "كأن رداءيه إذا قام علقا",
    "quafia": "q-د",
    "engSea": "el-tawil",
    "arabSea": "الطويل",
    "engTopic": "Short",
    "arabTopic": "قصائد قصيره",
    "poetId": 1806,
    "type": "عموديه",
    "order": 15,
    "link": "https://www.aldiwan.net/poem71175.html",
    "id": 74350
  },
  {
    "name": "عفا النحب بعدي فالعريشان فالبتر",
    "quafia": "q-ر",
    "engSea": "el-tawil",
    "arabSea": "الطويل",
    "engTopic": "Reproach",
    "arabTopic": "قصائد عتاب",
    "poetId": 1806,
    "type": "عموديه",
    "order": 16,
    "link": "https://www.aldiwan.net/poem71174.html",
    "id": 74351
  },
  {
    "name": "عفا بطن سهي من سليمى وصمعر",
    "quafia": "q-ر",
    "engSea": "el-tawil",
    "arabSea": "الطويل",
    "engTopic": "Reproach",
    "arabTopic": "قصائد عتاب",
    "poetId": 1806,
    "type": "عموديه",
    "order": 17,
    "link": "https://www.aldiwan.net/poem71173.html",
    "id": 74352
  },
  {
    "name": "عفا من آل خرقاء الستار",
    "quafia": "q-ر",
    "engSea": "el-wafer",
    "arabSea": "الوافر",
    "engTopic": "Satire",
    "arabTopic": "قصائد هجاء",
    "poetId": 1806,
    "type": "عموديه",
    "order": 18,
    "link": "https://www.aldiwan.net/poem71172.html",
    "id": 74353
  },
  {
    "name": "ومن لا تلد أسماء من آل عامر",
    "quafia": "q-ر",
    "engSea": "el-tawil",
    "arabSea": "الطويل",
    "engTopic": "Short",
    "arabTopic": "قصائد قصيره",
    "poetId": 1806,
    "type": "عموديه",
    "order": 19,
    "link": "https://www.aldiwan.net/poem71171.html",
    "id": 74354
  },
  {
    "name": "عبد السلام تأمل هل ترى ظعنا",
    "quafia": "q-ر",
    "engSea": "bassit",
    "arabSea": "البسيط",
    "engTopic": "Reproach",
    "arabTopic": "قصائد عتاب",
    "poetId": 1806,
    "type": "عموديه",
    "order": 20,
    "link": "https://www.aldiwan.net/poem71170.html",
    "id": 74355
  },
  {
    "name": "يا أخت بهم وذاك العبد ضاحية",
    "quafia": "q-ي",
    "engSea": "bassit",
    "arabSea": "البسيط",
    "engTopic": "Reproach",
    "arabTopic": "قصائد عتاب",
    "poetId": 1806,
    "type": "عموديه",
    "order": 21,
    "link": "https://www.aldiwan.net/poem71169.html",
    "id": 74356
  },
  {
    "name": "يا قبح الله صبيانا تجيء بهم",
    "quafia": "q-ي",
    "engSea": "bassit",
    "arabSea": "البسيط",
    "engTopic": "Condemnation",
    "arabTopic": "قصائد ذم",
    "poetId": 1806,
    "type": "عموديه",
    "order": 22,
    "link": "https://www.aldiwan.net/poem71168.html",
    "id": 74357
  },
  {
    "name": "يا أيها العفج السمين وقومه",
    "quafia": "q-ر",
    "engSea": "el-kamel",
    "arabSea": "الكامل",
    "engTopic": "Condemnation",
    "arabTopic": "قصائد ذم",
    "poetId": 1806,
    "type": "عموديه",
    "order": 23,
    "link": "https://www.aldiwan.net/poem71167.html",
    "id": 74358
  },
  {
    "name": "سرى بديار تغلب بين حوضي",
    "quafia": "q-ر",
    "engSea": "el-wafer",
    "arabSea": "الوافر",
    "engTopic": "Short",
    "arabTopic": "قصائد قصيره",
    "poetId": 1806,
    "type": "عموديه",
    "order": 24,
    "link": "https://www.aldiwan.net/poem71166.html",
    "id": 74359
  },
  {
    "name": "إذا شئت غناني على ظهر شرجع",
    "quafia": "q-ر",
    "engSea": "el-tawil",
    "arabSea": "الطويل",
    "engTopic": "Short",
    "arabTopic": "قصائد قصيره",
    "poetId": 1806,
    "type": "عموديه",
    "order": 25,
    "link": "https://www.aldiwan.net/poem71165.html",
    "id": 74360
  },
  {
    "name": "ورثنا أبانا حمرة اللون عامرا",
    "quafia": "q-ر",
    "engSea": "el-tawil",
    "arabSea": "الطويل",
    "engTopic": "Short",
    "arabTopic": "قصائد قصيره",
    "poetId": 1806,
    "type": "عموديه",
    "order": 26,
    "link": "https://www.aldiwan.net/poem71164.html",
    "id": 74361
  },
  {
    "name": "لطيبة ربع بالكليبين دارس",
    "quafia": "q-س",
    "engSea": "el-tawil",
    "arabSea": "الطويل",
    "engTopic": "Satire",
    "arabTopic": "قصائد هجاء",
    "poetId": 1806,
    "type": "عموديه",
    "order": 27,
    "link": "https://www.aldiwan.net/poem71163.html",
    "id": 74362
  },
  {
    "name": "ظعنت قطاة فما تقولك صانعا",
    "quafia": "q-ع",
    "engSea": "el-kamel",
    "arabSea": "الكامل",
    "engTopic": "Romance",
    "arabTopic": "قصائد رومنسيه",
    "poetId": 1806,
    "type": "عموديه",
    "order": 28,
    "link": "https://www.aldiwan.net/poem71162.html",
    "id": 74363
  },
  {
    "name": "لعمري لحي من عقيل لقيتهم",
    "quafia": "q-ك",
    "engSea": "el-tawil",
    "arabSea": "الطويل",
    "engTopic": "Satire",
    "arabTopic": "قصائد هجاء",
    "poetId": 1806,
    "type": "عموديه",
    "order": 29,
    "link": "https://www.aldiwan.net/poem71161.html",
    "id": 74364
  },
  {
    "name": "وإن أبا سفيان ليس بمولم",
    "quafia": "q-ك",
    "engSea": "el-tawil",
    "arabSea": "الطويل",
    "engTopic": "Short",
    "arabTopic": "قصائد قصيره",
    "poetId": 1806,
    "type": "عموديه",
    "order": 30,
    "link": "https://www.aldiwan.net/poem71160.html",
    "id": 74365
  },
  {
    "name": "أميم أثيبي قبل جد التزيل",
    "quafia": "q-ل",
    "engSea": "el-tawil",
    "arabSea": "الطويل",
    "engTopic": "Reproach",
    "arabTopic": "قصائد عتاب",
    "poetId": 1806,
    "type": "عموديه",
    "order": 31,
    "link": "https://www.aldiwan.net/poem71159.html",
    "id": 74366
  },
  {
    "name": "أيرسل مروان الأمير رسالة",
    "quafia": "q-ل",
    "engSea": "el-tawil",
    "arabSea": "الطويل",
    "engTopic": "Satire",
    "arabTopic": "قصائد هجاء",
    "poetId": 1806,
    "type": "عموديه",
    "order": 32,
    "link": "https://www.aldiwan.net/poem71158.html",
    "id": 74367
  },
  {
    "name": "وما مغزل ترعى بأرض تبالة",
    "quafia": "q-ل",
    "engSea": "el-tawil",
    "arabSea": "الطويل",
    "engTopic": "Reproach",
    "arabTopic": "قصائد عتاب",
    "poetId": 1806,
    "type": "عموديه",
    "order": 33,
    "link": "https://www.aldiwan.net/poem71157.html",
    "id": 74368
  },
  {
    "name": "ياصاحبي أقلا بعض إملالي",
    "quafia": "q-ل",
    "engSea": "bassit",
    "arabSea": "البسيط",
    "engTopic": "Short",
    "arabTopic": "قصائد قصيره",
    "poetId": 1806,
    "type": "عموديه",
    "order": 34,
    "link": "https://www.aldiwan.net/poem71156.html",
    "id": 74369
  },
  {
    "name": "لكاظمة الملاحة فإتركيها",
    "quafia": "q-ل",
    "engSea": "el-wafer",
    "arabSea": "الوافر",
    "engTopic": "Condemnation",
    "arabTopic": "قصائد ذم",
    "poetId": 1806,
    "type": "عموديه",
    "order": 35,
    "link": "https://www.aldiwan.net/poem71155.html",
    "id": 74370
  },
  {
    "name": "قلت له يا أخرم إبن مال",
    "quafia": "q-ل",
    "engSea": "el-rijz",
    "arabSea": "الرجز",
    "engTopic": "Reproach",
    "arabTopic": "قصائد عتاب",
    "poetId": 1806,
    "type": "عموديه",
    "order": 36,
    "link": "https://www.aldiwan.net/poem71154.html",
    "id": 74371
  },
  {
    "name": "أنا الذي إنتشلتها إنتشالا",
    "quafia": "q-ل",
    "engSea": "el-rijz",
    "arabSea": "الرجز",
    "engTopic": "Short",
    "arabTopic": "قصائد قصيره",
    "poetId": 1806,
    "type": "عموديه",
    "order": 37,
    "link": "https://www.aldiwan.net/poem71153.html",
    "id": 74372
  },
  {
    "name": "أنا الذي ضربتها بالمنصل",
    "quafia": "q-ل",
    "engSea": "el-rijz",
    "arabSea": "الرجز",
    "engTopic": "Praise",
    "arabTopic": "قصائد مدح",
    "poetId": 1806,
    "type": "عموديه",
    "order": 38,
    "link": "https://www.aldiwan.net/poem71152.html",
    "id": 74373
  },
  {
    "name": "إذا ما لقيتم راكبا متعمما",
    "quafia": "q-م",
    "engSea": "el-tawil",
    "arabSea": "الطويل",
    "engTopic": "Satire",
    "arabTopic": "قصائد هجاء",
    "poetId": 1806,
    "type": "عموديه",
    "order": 39,
    "link": "https://www.aldiwan.net/poem71151.html",
    "id": 74374
  },
  {
    "name": "تركت إبن هبار ورائي مجدلا",
    "quafia": "q-م",
    "engSea": "el-tawil",
    "arabSea": "الطويل",
    "engTopic": "Short",
    "arabTopic": "قصائد قصيره",
    "poetId": 1806,
    "type": "عموديه",
    "order": 40,
    "link": "https://www.aldiwan.net/poem71150.html",
    "id": 74375
  },
  {
    "name": "هل حبل مامة هذه مصروم",
    "quafia": "q-م",
    "engSea": "el-kamel",
    "arabSea": "الكامل",
    "engTopic": "Romance",
    "arabTopic": "قصائد رومنسيه",
    "poetId": 1806,
    "type": "عموديه",
    "order": 41,
    "link": "https://www.aldiwan.net/poem71149.html",
    "id": 74376
  },
  {
    "name": "نشدت زيادا والمقامة بيننا",
    "quafia": "q-م",
    "engSea": "el-tawil",
    "arabSea": "الطويل",
    "engTopic": "Reproach",
    "arabTopic": "قصائد عتاب",
    "poetId": 1806,
    "type": "عموديه",
    "order": 42,
    "link": "https://www.aldiwan.net/poem71148.html",
    "id": 74377
  },
  {
    "name": "نهيت زيادا والمهامه بيننا",
    "quafia": "q-م",
    "engSea": "el-tawil",
    "arabSea": "الطويل",
    "engTopic": "Reproach",
    "arabTopic": "قصائد عتاب",
    "poetId": 1806,
    "type": "عموديه",
    "order": 43,
    "link": "https://www.aldiwan.net/poem71147.html",
    "id": 74378
  },
  {
    "name": "سقى الله ما بين الرجام وغمرة",
    "quafia": "q-ن",
    "engSea": "el-tawil",
    "arabSea": "الطويل",
    "engTopic": "Short",
    "arabTopic": "قصائد قصيره",
    "poetId": 1806,
    "type": "عموديه",
    "order": 44,
    "link": "https://www.aldiwan.net/poem71146.html",
    "id": 74379
  },
  {
    "name": "سقى الله ما بين الشطون وغمرة",
    "quafia": "q-ن",
    "engSea": "el-tawil",
    "arabSea": "الطويل",
    "engTopic": "Reproach",
    "arabTopic": "قصائد عتاب",
    "poetId": 1806,
    "type": "عموديه",
    "order": 45,
    "link": "https://www.aldiwan.net/poem71145.html",
    "id": 74380
  },
  {
    "name": "لقد ولدتني حرة ربعية",
    "quafia": "q-ن",
    "engSea": "el-tawil",
    "arabSea": "الطويل",
    "engTopic": "Praise",
    "arabTopic": "قصائد مدح",
    "poetId": 1806,
    "type": "عموديه",
    "order": 46,
    "link": "https://www.aldiwan.net/poem71144.html",
    "id": 74381
  },
  {
    "name": "أعالي أعلى الله جدك عاليا",
    "quafia": "q-ي",
    "engSea": "el-tawil",
    "arabSea": "الطويل",
    "engTopic": "General",
    "arabTopic": "قصائد عامه",
    "poetId": 1806,
    "type": "عموديه",
    "order": 47,
    "link": "https://www.aldiwan.net/poem71143.html",
    "id": 74382
  },
  {
    "name": "أبا خالد يا انفر فلست بخالد",
    "quafia": "q-د",
    "engSea": "el-tawil",
    "arabSea": "الطويل",
    "engTopic": "Condemnation",
    "arabTopic": "قصائد ذم",
    "poetId": 1807,
    "type": "عموديه",
    "order": 1,
    "link": "https://www.aldiwan.net/poem71142.html",
    "id": 74383
  },
  {
    "name": "لعمرك إني في الحياة لزاهد",
    "quafia": "q-م",
    "engSea": "el-tawil",
    "arabSea": "الطويل",
    "engTopic": "Romance",
    "arabTopic": "قصائد رومنسيه",
    "poetId": 1807,
    "type": "عموديه",
    "order": 2,
    "link": "https://www.aldiwan.net/poem71141.html",
    "id": 74384
  },
  {
    "name": "إذا قلت تسلو النفس أو تنتهي المنى",
    "quafia": "q-م",
    "engSea": "el-tawil",
    "arabSea": "الطويل",
    "engTopic": "Romance",
    "arabTopic": "قصائد رومنسيه",
    "poetId": 1807,
    "type": "عموديه",
    "order": 3,
    "link": "https://www.aldiwan.net/poem71140.html",
    "id": 74385
  },
  {
    "name": "أقول لها وقد طارت شعاعا",
    "quafia": "q-ي",
    "engSea": "el-wafer",
    "arabSea": "الوافر",
    "engTopic": "Satire",
    "arabTopic": "قصائد هجاء",
    "poetId": 1807,
    "type": "عموديه",
    "order": 4,
    "link": "https://www.aldiwan.net/poem71139.html",
    "id": 74386
  },
  {
    "name": "يا رب ظل عقاب قد وقيت بها",
    "quafia": "q-د",
    "engSea": "bassit",
    "arabSea": "البسيط",
    "engTopic": "Elegy",
    "arabTopic": "قصائد رثاء",
    "poetId": 1807,
    "type": "عموديه",
    "order": 5,
    "link": "https://www.aldiwan.net/poem71138.html",
    "id": 74387
  },
  {
    "name": "إلى كم تغاريني السيوف ولا أرى",
    "quafia": "q-ي",
    "engSea": "el-tawil",
    "arabSea": "الطويل",
    "engTopic": "Satire",
    "arabTopic": "قصائد هجاء",
    "poetId": 1807,
    "type": "عموديه",
    "order": 6,
    "link": "https://www.aldiwan.net/poem71137.html",
    "id": 74388
  },
  {
    "name": "لا يركنن أحد إلى الإحجام",
    "quafia": "q-م",
    "engSea": "el-kamel",
    "arabSea": "الكامل",
    "engTopic": "Elegy",
    "arabTopic": "قصائد رثاء",
    "poetId": 1807,
    "type": "عموديه",
    "order": 7,
    "link": "https://www.aldiwan.net/poem71136.html",
    "id": 74389
  },
  {
    "name": "ألا أيها الباغي البراز تقربن",
    "quafia": "q-ب",
    "engSea": "el-tawil",
    "arabSea": "الطويل",
    "engTopic": "Elegy",
    "arabTopic": "قصائد رثاء",
    "poetId": 1807,
    "type": "عموديه",
    "order": 8,
    "link": "https://www.aldiwan.net/poem71135.html",
    "id": 74390
  },
  {
    "name": "يا نفس لا يلهينك الأمل",
    "quafia": "q-ل",
    "engSea": "el-monsareh",
    "arabSea": "المنسرح",
    "engTopic": "Short",
    "arabTopic": "قصائد قصيره",
    "poetId": 1807,
    "type": "عموديه",
    "order": 9,
    "link": "https://www.aldiwan.net/poem71134.html",
    "id": 74391
  },
  {
    "name": "ألم يأتها أني لعبت بخالد",
    "quafia": "q-ب",
    "engSea": "el-tawil",
    "arabSea": "الطويل",
    "engTopic": "Condemnation",
    "arabTopic": "قصائد ذم",
    "poetId": 1807,
    "type": "عموديه",
    "order": 10,
    "link": "https://www.aldiwan.net/poem71133.html",
    "id": 74392
  },
  {
    "name": "ألا قل لبشر إن بشرا مصبح",
    "quafia": "q-ب",
    "engSea": "el-tawil",
    "arabSea": "الطويل",
    "engTopic": "Elegy",
    "arabTopic": "قصائد رثاء",
    "poetId": 1807,
    "type": "عموديه",
    "order": 11,
    "link": "https://www.aldiwan.net/poem71132.html",
    "id": 74393
  },
  {
    "name": "إن شجانا في الوغى المهلب",
    "quafia": "q-ب",
    "engSea": "el-rijz",
    "arabSea": "الرجز",
    "engTopic": "General",
    "arabTopic": "قصائد عامه",
    "poetId": 1807,
    "type": "عموديه",
    "order": 12,
    "link": "https://www.aldiwan.net/poem71131.html",
    "id": 74394
  },
  {
    "name": "سبحان ربي باعث العباد",
    "quafia": "q-د",
    "engSea": "el-rijz",
    "arabSea": "الرجز",
    "engTopic": "Short",
    "arabTopic": "قصائد قصيره",
    "poetId": 1807,
    "type": "عموديه",
    "order": 13,
    "link": "https://www.aldiwan.net/poem71130.html",
    "id": 74395
  },
  {
    "name": "أن يلقني بحده المهلب",
    "quafia": "q-ب",
    "engSea": "el-rijz",
    "arabSea": "الرجز",
    "engTopic": "Elegy",
    "arabTopic": "قصائد رثاء",
    "poetId": 1807,
    "type": "عموديه",
    "order": 14,
    "link": "https://www.aldiwan.net/poem71129.html",
    "id": 74396
  },
  {
    "name": "حتى متى تخطئني الشهاده",
    "quafia": "q-د",
    "engSea": "el-rijz",
    "arabSea": "الرجز",
    "engTopic": "Elegy",
    "arabTopic": "قصائد رثاء",
    "poetId": 1807,
    "type": "عموديه",
    "order": 15,
    "link": "https://www.aldiwan.net/poem71128.html",
    "id": 74397
  },
  {
    "name": "لعمري لئن كنا أصبنا بنافع",
    "quafia": "q-ب",
    "engSea": "el-tawil",
    "arabSea": "الطويل",
    "engTopic": "Elegy",
    "arabTopic": "قصائد رثاء",
    "poetId": 1807,
    "type": "عموديه",
    "order": 16,
    "link": "https://www.aldiwan.net/poem71127.html",
    "id": 74398
  },
  {
    "name": "لعمري لئن كان المزوني فارسا",
    "quafia": "q-س",
    "engSea": "el-tawil",
    "arabSea": "الطويل",
    "engTopic": "Praise",
    "arabTopic": "قصائد مدح",
    "poetId": 1807,
    "type": "عموديه",
    "order": 17,
    "link": "https://www.aldiwan.net/poem71126.html",
    "id": 74399
  },
  {
    "name": "كان المزوني إذا بدا له",
    "quafia": "q-ل",
    "engSea": "el-rijz",
    "arabSea": "الرجز",
    "engTopic": "Satire",
    "arabTopic": "قصائد هجاء",
    "poetId": 1807,
    "type": "عموديه",
    "order": 18,
    "link": "https://www.aldiwan.net/poem71125.html",
    "id": 74400
  },
  {
    "name": "أقول لنفسي حين طال حصارها",
    "quafia": "q-ر",
    "engSea": "el-tawil",
    "arabSea": "الطويل",
    "engTopic": "Elegy",
    "arabTopic": "قصائد رثاء",
    "poetId": 1807,
    "type": "عموديه",
    "order": 19,
    "link": "https://www.aldiwan.net/poem71124.html",
    "id": 74401
  },
  {
    "name": "ورب مصاليت نشاط إلى الوغى",
    "quafia": "q-م",
    "engSea": "el-tawil",
    "arabSea": "الطويل",
    "engTopic": "Praise",
    "arabTopic": "قصائد مدح",
    "poetId": 1807,
    "type": "عموديه",
    "order": 20,
    "link": "https://www.aldiwan.net/poem71123.html",
    "id": 74402
  },
  {
    "name": "لشتان ما بين ابن جعد وبيننا",
    "quafia": "q-ر",
    "engSea": "el-tawil",
    "arabSea": "الطويل",
    "engTopic": "Praise",
    "arabTopic": "قصائد مدح",
    "poetId": 1807,
    "type": "عموديه",
    "order": 21,
    "link": "https://www.aldiwan.net/poem71122.html",
    "id": 74403
  },
  {
    "name": "أنا أبو نعامة الشيخ الهبل",
    "quafia": "q-ل",
    "engSea": "el-rijz",
    "arabSea": "الرجز",
    "engTopic": "Praise",
    "arabTopic": "قصائد مدح",
    "poetId": 1807,
    "type": "عموديه",
    "order": 22,
    "link": "https://www.aldiwan.net/poem71121.html",
    "id": 74404
  },
  {
    "name": "ترفق أيها الحادي بعشاق",
    "quafia": "q-ق",
    "engSea": "el-dobit",
    "arabSea": "الدوبيت",
    "engTopic": "Longing",
    "arabTopic": "قصائد شوق",
    "poetId": 1808,
    "type": "عموديه",
    "order": 1,
    "link": "https://www.aldiwan.net/poem70974.html",
    "id": 74405
  },
  {
    "name": "طرقتك زينب بعدما طال الكرى",
    "quafia": "q-ب",
    "engSea": "el-kamel",
    "arabSea": "الكامل",
    "engTopic": "Romance",
    "arabTopic": "قصائد رومنسيه",
    "poetId": 1808,
    "type": "عموديه",
    "order": 2,
    "link": "https://www.aldiwan.net/poem70958.html",
    "id": 74406
  },
  {
    "name": "وغيث مريع لم يجدع نباته",
    "quafia": "q-ب",
    "engSea": "el-tawil",
    "arabSea": "الطويل",
    "engTopic": "Satire",
    "arabTopic": "قصائد هجاء",
    "poetId": 1808,
    "type": "عموديه",
    "order": 3,
    "link": "https://www.aldiwan.net/poem70957.html",
    "id": 74407
  },
  {
    "name": "عفا بطحان من قريش فيثرب",
    "quafia": "q-ب",
    "engSea": "el-tawil",
    "arabSea": "الطويل",
    "engTopic": "Praise",
    "arabTopic": "قصائد مدح",
    "poetId": 1808,
    "type": "عموديه",
    "order": 4,
    "link": "https://www.aldiwan.net/poem70956.html",
    "id": 74408
  },
  {
    "name": "سل الدار من جنبي حبر فواهب",
    "quafia": "q-ح",
    "engSea": "el-tawil",
    "arabSea": "الطويل",
    "engTopic": "Praise",
    "arabTopic": "قصائد مدح",
    "poetId": 1808,
    "type": "عموديه",
    "order": 5,
    "link": "https://www.aldiwan.net/poem70955.html",
    "id": 74409
  },
  {
    "name": "دعتنا بكهف من كنا بين دعوة",
    "quafia": "q-ح",
    "engSea": "el-tawil",
    "arabSea": "الطويل",
    "engTopic": "Romance",
    "arabTopic": "قصائد رومنسيه",
    "poetId": 1808,
    "type": "عموديه",
    "order": 6,
    "link": "https://www.aldiwan.net/poem70954.html",
    "id": 74410
  },
  {
    "name": "هل القلب عن دهماء سال فمسمح",
    "quafia": "q-ح",
    "engSea": "el-tawil",
    "arabSea": "الطويل",
    "engTopic": "Romance",
    "arabTopic": "قصائد رومنسيه",
    "poetId": 1808,
    "type": "عموديه",
    "order": 7,
    "link": "https://www.aldiwan.net/poem70953.html",
    "id": 74411
  },
  {
    "name": "أمن رسم دار بالجناح عرفتها",
    "quafia": "q-د",
    "engSea": "el-tawil",
    "arabSea": "الطويل",
    "engTopic": "Praise",
    "arabTopic": "قصائد مدح",
    "poetId": 1808,
    "type": "عموديه",
    "order": 8,
    "link": "https://www.aldiwan.net/poem70952.html",
    "id": 74412
  },
  {
    "name": "أاليوم بان الحي أم واعدوا غدا",
    "quafia": "q-د",
    "engSea": "el-tawil",
    "arabSea": "الطويل",
    "engTopic": "Reproach",
    "arabTopic": "قصائد عتاب",
    "poetId": 1808,
    "type": "عموديه",
    "order": 9,
    "link": "https://www.aldiwan.net/poem70951.html",
    "id": 74413
  },
  {
    "name": "جزى الله سعدا بالأبارق نعمة",
    "quafia": "q-د",
    "engSea": "el-tawil",
    "arabSea": "الطويل",
    "engTopic": "Short",
    "arabTopic": "قصائد قصيره",
    "poetId": 1808,
    "type": "عموديه",
    "order": 10,
    "link": "https://www.aldiwan.net/poem70950.html",
    "id": 74414
  },
  {
    "name": "يا حر أمسيت شيخا قد وهى بصري",
    "quafia": "q-ي",
    "engSea": "bassit",
    "arabSea": "البسيط",
    "engTopic": "Reproach",
    "arabTopic": "قصائد عتاب",
    "poetId": 1808,
    "type": "عموديه",
    "order": 11,
    "link": "https://www.aldiwan.net/poem70949.html",
    "id": 74415
  },
  {
    "name": "هل تعرف الدار قفرا لا أنيس بها",
    "quafia": "q-ر",
    "engSea": "bassit",
    "arabSea": "البسيط",
    "engTopic": "Elegy",
    "arabTopic": "قصائد رثاء",
    "poetId": 1808,
    "type": "عموديه",
    "order": 12,
    "link": "https://www.aldiwan.net/poem70948.html",
    "id": 74416
  },
  {
    "name": "هل أنت تخبر عنها كيف سيرتها",
    "quafia": "q-ر",
    "engSea": "bassit",
    "arabSea": "البسيط",
    "engTopic": "Short",
    "arabTopic": "قصائد قصيره",
    "poetId": 1808,
    "type": "عموديه",
    "order": 13,
    "link": "https://www.aldiwan.net/poem70947.html",
    "id": 74417
  },
  {
    "name": "خفرت على قيس فأدى خفارتي",
    "quafia": "q-ر",
    "engSea": "el-tawil",
    "arabSea": "الطويل",
    "engTopic": "Satire",
    "arabTopic": "قصائد هجاء",
    "poetId": 1808,
    "type": "عموديه",
    "order": 14,
    "link": "https://www.aldiwan.net/poem70946.html",
    "id": 74418
  },
  {
    "name": "يا صاحبي انظراني لا عدمتكما",
    "quafia": "q-ر",
    "engSea": "bassit",
    "arabSea": "البسيط",
    "engTopic": "Reproach",
    "arabTopic": "قصائد عتاب",
    "poetId": 1808,
    "type": "عموديه",
    "order": 15,
    "link": "https://www.aldiwan.net/poem70945.html",
    "id": 74419
  },
  {
    "name": "لمن الديار بجانب الأحفار",
    "quafia": "q-ر",
    "engSea": "el-kamel",
    "arabSea": "الكامل",
    "engTopic": "Satire",
    "arabTopic": "قصائد هجاء",
    "poetId": 1808,
    "type": "عموديه",
    "order": 16,
    "link": "https://www.aldiwan.net/poem70944.html",
    "id": 74420
  },
  {
    "name": "يا دار كبشة تلك لم تتغير",
    "quafia": "q-ر",
    "engSea": "el-kamel",
    "arabSea": "الكامل",
    "engTopic": "Sadness",
    "arabTopic": "قصائد حزينه",
    "poetId": 1808,
    "type": "عموديه",
    "order": 17,
    "link": "https://www.aldiwan.net/poem70943.html",
    "id": 74421
  },
  {
    "name": "تأمل خليلي هل ترى ضوء بارق",
    "quafia": "q-ر",
    "engSea": "el-tawil",
    "arabSea": "الطويل",
    "engTopic": "General",
    "arabTopic": "قصائد عامه",
    "poetId": 1808,
    "type": "عموديه",
    "order": 18,
    "link": "https://www.aldiwan.net/poem70942.html",
    "id": 74422
  },
  {
    "name": "ألم تر أن القلب ثاب وأبصرا",
    "quafia": "q-ر",
    "engSea": "el-tawil",
    "arabSea": "الطويل",
    "engTopic": "Reproach",
    "arabTopic": "قصائد عتاب",
    "poetId": 1808,
    "type": "عموديه",
    "order": 19,
    "link": "https://www.aldiwan.net/poem70941.html",
    "id": 74423
  },
  {
    "name": "قفا في دار أهلي فاسألاها",
    "quafia": "q-ر",
    "engSea": "el-wafer",
    "arabSea": "الوافر",
    "engTopic": "Praise",
    "arabTopic": "قصائد مدح",
    "poetId": 1808,
    "type": "عموديه",
    "order": 20,
    "link": "https://www.aldiwan.net/poem70940.html",
    "id": 74424
  },
  {
    "name": "تأوبني الداء الذي أنا حاذره",
    "quafia": "q-ر",
    "engSea": "el-tawil",
    "arabSea": "الطويل",
    "engTopic": "Elegy",
    "arabTopic": "قصائد رثاء",
    "poetId": 1808,
    "type": "عموديه",
    "order": 21,
    "link": "https://www.aldiwan.net/poem70939.html",
    "id": 74425
  },
  {
    "name": "أمسى بفيحان فنفر من قطا",
    "quafia": "q-س",
    "engSea": "el-kamel",
    "arabSea": "الكامل",
    "engTopic": "Short",
    "arabTopic": "قصائد قصيره",
    "poetId": 1808,
    "type": "عموديه",
    "order": 22,
    "link": "https://www.aldiwan.net/poem70938.html",
    "id": 74426
  },
  {
    "name": "ألا قف بالمنازل والربوع",
    "quafia": "q-ع",
    "engSea": "el-wafer",
    "arabSea": "الوافر",
    "engTopic": "Elegy",
    "arabTopic": "قصائد رثاء",
    "poetId": 1808,
    "type": "عموديه",
    "order": 23,
    "link": "https://www.aldiwan.net/poem70937.html",
    "id": 74427
  },
  {
    "name": "للمازنية مصطاف ومرتبع",
    "quafia": "q-ع",
    "engSea": "bassit",
    "arabSea": "البسيط",
    "engTopic": "Praise",
    "arabTopic": "قصائد مدح",
    "poetId": 1808,
    "type": "عموديه",
    "order": 24,
    "link": "https://www.aldiwan.net/poem70936.html",
    "id": 74428
  },
  {
    "name": "شطت نوى من يحل السر فالشرفا",
    "quafia": "q-ف",
    "engSea": "bassit",
    "arabSea": "البسيط",
    "engTopic": "Satire",
    "arabTopic": "قصائد هجاء",
    "poetId": 1808,
    "type": "عموديه",
    "order": 25,
    "link": "https://www.aldiwan.net/poem70935.html",
    "id": 74429
  },
  {
    "name": "عفا من سليمى ذو كلاف فمنكف",
    "quafia": "q-ف",
    "engSea": "el-tawil",
    "arabSea": "الطويل",
    "engTopic": "Praise",
    "arabTopic": "قصائد مدح",
    "poetId": 1808,
    "type": "عموديه",
    "order": 26,
    "link": "https://www.aldiwan.net/poem70934.html",
    "id": 74430
  },
  {
    "name": "بكت أم بشر أن تبدد رهطها",
    "quafia": "q-ك",
    "engSea": "el-tawil",
    "arabSea": "الطويل",
    "engTopic": "Elegy",
    "arabTopic": "قصائد رثاء",
    "poetId": 1808,
    "type": "عموديه",
    "order": 27,
    "link": "https://www.aldiwan.net/poem70933.html",
    "id": 74431
  },
  {
    "name": "أبلغ حنيفة أن أول سبقهم",
    "quafia": "q-ك",
    "engSea": "el-kamel",
    "arabSea": "الكامل",
    "engTopic": "Praise",
    "arabTopic": "قصائد مدح",
    "poetId": 1808,
    "type": "عموديه",
    "order": 28,
    "link": "https://www.aldiwan.net/poem70932.html",
    "id": 74432
  },
  {
    "name": "ذر العين تسفح في الديار فلا أرى",
    "quafia": "q-ا",
    "engSea": "el-tawil",
    "arabSea": "الطويل",
    "engTopic": "Elegy",
    "arabTopic": "قصائد رثاء",
    "poetId": 1808,
    "type": "عموديه",
    "order": 29,
    "link": "https://www.aldiwan.net/poem70931.html",
    "id": 74433
  },
  {
    "name": "تجانف ربع من كبيشة منجلا",
    "quafia": "q-ا",
    "engSea": "el-tawil",
    "arabSea": "الطويل",
    "engTopic": "General",
    "arabTopic": "قصائد عامه",
    "poetId": 1808,
    "type": "عموديه",
    "order": 30,
    "link": "https://www.aldiwan.net/poem70930.html",
    "id": 74434
  },
  {
    "name": "سل المنازل كيف صرم الواصل",
    "quafia": "q-ل",
    "engSea": "el-kamel",
    "arabSea": "الكامل",
    "engTopic": "Elegy",
    "arabTopic": "قصائد رثاء",
    "poetId": 1808,
    "type": "عموديه",
    "order": 31,
    "link": "https://www.aldiwan.net/poem70929.html",
    "id": 74435
  },
  {
    "name": "دعتنا عتيبة من عالج",
    "quafia": "q-ا",
    "engSea": "el-mota9areb",
    "arabSea": "المتقارب",
    "engTopic": "Satire",
    "arabTopic": "قصائد هجاء",
    "poetId": 1808,
    "type": "عموديه",
    "order": 32,
    "link": "https://www.aldiwan.net/poem70928.html",
    "id": 74436
  },
  {
    "name": "هل أنت محيي الربع أم أنت سائله",
    "quafia": "q-ل",
    "engSea": "el-tawil",
    "arabSea": "الطويل",
    "engTopic": "Reproach",
    "arabTopic": "قصائد عتاب",
    "poetId": 1808,
    "type": "عموديه",
    "order": 33,
    "link": "https://www.aldiwan.net/poem70927.html",
    "id": 74437
  },
  {
    "name": "سائل بكبشة دارس الأطلال",
    "quafia": "q-ل",
    "engSea": "el-kamel",
    "arabSea": "الكامل",
    "engTopic": "Satire",
    "arabTopic": "قصائد هجاء",
    "poetId": 1808,
    "type": "عموديه",
    "order": 34,
    "link": "https://www.aldiwan.net/poem70926.html",
    "id": 74438
  },
  {
    "name": "أحار بن كعب ثم لا شيء بعده",
    "quafia": "q-ل",
    "engSea": "el-tawil",
    "arabSea": "الطويل",
    "engTopic": "Condemnation",
    "arabTopic": "قصائد ذم",
    "poetId": 1808,
    "type": "عموديه",
    "order": 35,
    "link": "https://www.aldiwan.net/poem70925.html",
    "id": 74439
  },
  {
    "name": "أناظر الوصل أم غاد فمصروم",
    "quafia": "q-م",
    "engSea": "bassit",
    "arabSea": "البسيط",
    "engTopic": "Reproach",
    "arabTopic": "قصائد عتاب",
    "poetId": 1808,
    "type": "عموديه",
    "order": 36,
    "link": "https://www.aldiwan.net/poem70924.html",
    "id": 74440
  },
  {
    "name": "خليلي عوجا حييا أم خشرم",
    "quafia": "q-ي",
    "engSea": "el-tawil",
    "arabSea": "الطويل",
    "engTopic": "Reproach",
    "arabTopic": "قصائد عتاب",
    "poetId": 1808,
    "type": "عموديه",
    "order": 37,
    "link": "https://www.aldiwan.net/poem70923.html",
    "id": 74441
  },
  {
    "name": "ألا طرقتنا بالمدينة بعدم",
    "quafia": "q-م",
    "engSea": "el-tawil",
    "arabSea": "الطويل",
    "engTopic": "Satire",
    "arabTopic": "قصائد هجاء",
    "poetId": 1808,
    "type": "عموديه",
    "order": 38,
    "link": "https://www.aldiwan.net/poem70922.html",
    "id": 74442
  },
  {
    "name": "وغيث تبطنت قريانه",
    "quafia": "q-ن",
    "engSea": "el-mota9areb",
    "arabSea": "المتقارب",
    "engTopic": "Reproach",
    "arabTopic": "قصائد عتاب",
    "poetId": 1808,
    "type": "عموديه",
    "order": 39,
    "link": "https://www.aldiwan.net/poem70921.html",
    "id": 74443
  },
  {
    "name": "قد قرق الدهر بين الحي بالظعن",
    "quafia": "q-ن",
    "engSea": "bassit",
    "arabSea": "البسيط",
    "engTopic": "Parting",
    "arabTopic": "قصائد فراق",
    "poetId": 1808,
    "type": "عموديه",
    "order": 40,
    "link": "https://www.aldiwan.net/poem70920.html",
    "id": 74444
  },
  {
    "name": "أأخطل لم ذكرت نساء قيس",
    "quafia": "q-ن",
    "engSea": "el-wafer",
    "arabSea": "الوافر",
    "engTopic": "Satire",
    "arabTopic": "قصائد هجاء",
    "poetId": 1808,
    "type": "عموديه",
    "order": 41,
    "link": "https://www.aldiwan.net/poem70919.html",
    "id": 74445
  },
  {
    "name": "طاف الخيال بنا ركبا يمانينا",
    "quafia": "q-ن",
    "engSea": "bassit",
    "arabSea": "البسيط",
    "engTopic": "Ghazal",
    "arabTopic": "قصائد غزل",
    "poetId": 1808,
    "type": "عموديه",
    "order": 42,
    "link": "https://www.aldiwan.net/poem70918.html",
    "id": 74446
  },
  {
    "name": "ألا يا ديار الحي بالسبعان",
    "quafia": "q-ن",
    "engSea": "el-tawil",
    "arabSea": "الطويل",
    "engTopic": "Romance",
    "arabTopic": "قصائد رومنسيه",
    "poetId": 1808,
    "type": "عموديه",
    "order": 43,
    "link": "https://www.aldiwan.net/poem70917.html",
    "id": 74447
  },
  {
    "name": "فهل يبلغني أهل دهماء حرة",
    "quafia": "q-ن",
    "engSea": "el-tawil",
    "arabSea": "الطويل",
    "engTopic": "Short",
    "arabTopic": "قصائد قصيره",
    "poetId": 1808,
    "type": "عموديه",
    "order": 44,
    "link": "https://www.aldiwan.net/poem70916.html",
    "id": 74448
  },
  {
    "name": "فقل للحماس يترك الفخر إنما",
    "quafia": "q-ن",
    "engSea": "el-tawil",
    "arabSea": "الطويل",
    "engTopic": "Praise",
    "arabTopic": "قصائد مدح",
    "poetId": 1808,
    "type": "عموديه",
    "order": 45,
    "link": "https://www.aldiwan.net/poem70915.html",
    "id": 74449
  },
  {
    "name": "وجاءت به حياكة عركية",
    "quafia": "q-ن",
    "engSea": "el-tawil",
    "arabSea": "الطويل",
    "engTopic": "Short",
    "arabTopic": "قصائد قصيره",
    "poetId": 1808,
    "type": "عموديه",
    "order": 46,
    "link": "https://www.aldiwan.net/poem70914.html",
    "id": 74450
  },
  {
    "name": "ونحن منعنا البحر أن يشربوا به",
    "quafia": "q-ن",
    "engSea": "el-tawil",
    "arabSea": "الطويل",
    "engTopic": "Short",
    "arabTopic": "قصائد قصيره",
    "poetId": 1808,
    "type": "عموديه",
    "order": 47,
    "link": "https://www.aldiwan.net/poem70913.html",
    "id": 74451
  },
  {
    "name": "وقد دق منها الخصر حتى وشاحها",
    "quafia": "q-ب",
    "engSea": "el-tawil",
    "arabSea": "الطويل",
    "engTopic": "Short",
    "arabTopic": "قصائد قصيره",
    "poetId": 1808,
    "type": "عموديه",
    "order": 48,
    "link": "https://www.aldiwan.net/poem70912.html",
    "id": 74452
  },
  {
    "name": "ولم أصطبح صهباء صافية القذى",
    "quafia": "q-ب",
    "engSea": "el-tawil",
    "arabSea": "الطويل",
    "engTopic": "Short",
    "arabTopic": "قصائد قصيره",
    "poetId": 1808,
    "type": "عموديه",
    "order": 49,
    "link": "https://www.aldiwan.net/poem70911.html",
    "id": 74453
  },
  {
    "name": "هل كنت إلا مجنا تتقون به",
    "quafia": "q-ي",
    "engSea": "bassit",
    "arabSea": "البسيط",
    "engTopic": "Short",
    "arabTopic": "قصائد قصيره",
    "poetId": 1808,
    "type": "عموديه",
    "order": 50,
    "link": "https://www.aldiwan.net/poem70910.html",
    "id": 74454
  },
  {
    "name": "إلى كبد كأن منهاة سوطها",
    "quafia": "q-ب",
    "engSea": "el-tawil",
    "arabSea": "الطويل",
    "engTopic": "Short",
    "arabTopic": "قصائد قصيره",
    "poetId": 1808,
    "type": "عموديه",
    "order": 51,
    "link": "https://www.aldiwan.net/poem70909.html",
    "id": 74455
  },
  {
    "name": "وأصفر عطاف إذا راح ربه",
    "quafia": "q-ب",
    "engSea": "el-tawil",
    "arabSea": "الطويل",
    "engTopic": "Short",
    "arabTopic": "قصائد قصيره",
    "poetId": 1808,
    "type": "عموديه",
    "order": 52,
    "link": "https://www.aldiwan.net/poem70908.html",
    "id": 74456
  },
  {
    "name": "خزامى وسعدان كأن رياضها",
    "quafia": "q-ب",
    "engSea": "el-tawil",
    "arabSea": "الطويل",
    "engTopic": "Short",
    "arabTopic": "قصائد قصيره",
    "poetId": 1808,
    "type": "عموديه",
    "order": 53,
    "link": "https://www.aldiwan.net/poem70907.html",
    "id": 74457
  },
  {
    "name": "تقدم قيس كل يوم كريهة",
    "quafia": "q-ب",
    "engSea": "el-tawil",
    "arabSea": "الطويل",
    "engTopic": "Short",
    "arabTopic": "قصائد قصيره",
    "poetId": 1808,
    "type": "عموديه",
    "order": 54,
    "link": "https://www.aldiwan.net/poem70906.html",
    "id": 74458
  },
  {
    "name": "وغيث أسال الله مهجة نفسه",
    "quafia": "q-ب",
    "engSea": "el-tawil",
    "arabSea": "الطويل",
    "engTopic": "Praise",
    "arabTopic": "قصائد مدح",
    "poetId": 1808,
    "type": "عموديه",
    "order": 55,
    "link": "https://www.aldiwan.net/poem70905.html",
    "id": 74459
  },
  {
    "name": "مصامص ما ذاق يوما قتا",
    "quafia": "q-ت",
    "engSea": "el-rijz",
    "arabSea": "الرجز",
    "engTopic": "Short",
    "arabTopic": "قصائد قصيره",
    "poetId": 1808,
    "type": "عموديه",
    "order": 56,
    "link": "https://www.aldiwan.net/poem70904.html",
    "id": 74460
  },
  {
    "name": "سبتني بعيني جؤذر حفلتهما",
    "quafia": "q-ح",
    "engSea": "el-tawil",
    "arabSea": "الطويل",
    "engTopic": "Satire",
    "arabTopic": "قصائد هجاء",
    "poetId": 1808,
    "type": "عموديه",
    "order": 57,
    "link": "https://www.aldiwan.net/poem70903.html",
    "id": 74461
  },
  {
    "name": "لحقنا بحي أوبوا السير بعدما",
    "quafia": "q-ح",
    "engSea": "el-tawil",
    "arabSea": "الطويل",
    "engTopic": "Short",
    "arabTopic": "قصائد قصيره",
    "poetId": 1808,
    "type": "عموديه",
    "order": 58,
    "link": "https://www.aldiwan.net/poem70902.html",
    "id": 74462
  },
  {
    "name": "وهم ثغروا أقرانهم بمضرس",
    "quafia": "q-ح",
    "engSea": "el-tawil",
    "arabSea": "الطويل",
    "engTopic": "Short",
    "arabTopic": "قصائد قصيره",
    "poetId": 1808,
    "type": "عموديه",
    "order": 59,
    "link": "https://www.aldiwan.net/poem70901.html",
    "id": 74463
  },
  {
    "name": "أقامت به حد الربيع وجارها",
    "quafia": "q-ح",
    "engSea": "el-tawil",
    "arabSea": "الطويل",
    "engTopic": "Short",
    "arabTopic": "قصائد قصيره",
    "poetId": 1808,
    "type": "عموديه",
    "order": 60,
    "link": "https://www.aldiwan.net/poem70900.html",
    "id": 74464
  },
  {
    "name": "عقاب عقنباة كأن وظيفها",
    "quafia": "q-ح",
    "engSea": "el-tawil",
    "arabSea": "الطويل",
    "engTopic": "Short",
    "arabTopic": "قصائد قصيره",
    "poetId": 1808,
    "type": "عموديه",
    "order": 61,
    "link": "https://www.aldiwan.net/poem70899.html",
    "id": 74465
  },
  {
    "name": "تمور بضبعيها وترمي بجوزها",
    "quafia": "q-ح",
    "engSea": "el-tawil",
    "arabSea": "الطويل",
    "engTopic": "Short",
    "arabTopic": "قصائد قصيره",
    "poetId": 1808,
    "type": "عموديه",
    "order": 62,
    "link": "https://www.aldiwan.net/poem70898.html",
    "id": 74466
  },
  {
    "name": "فكيف لنا بالشرب إن لم تكن لنا",
    "quafia": "q-د",
    "engSea": "el-tawil",
    "arabSea": "الطويل",
    "engTopic": "Short",
    "arabTopic": "قصائد قصيره",
    "poetId": 1808,
    "type": "عموديه",
    "order": 63,
    "link": "https://www.aldiwan.net/poem70897.html",
    "id": 74467
  },
  {
    "name": "ولا تقولن زهوا ما تخبرني",
    "quafia": "q-ر",
    "engSea": "bassit",
    "arabSea": "البسيط",
    "engTopic": "Short",
    "arabTopic": "قصائد قصيره",
    "poetId": 1808,
    "type": "عموديه",
    "order": 64,
    "link": "https://www.aldiwan.net/poem70896.html",
    "id": 74468
  },
  {
    "name": "يروي قوامح قبل الصبح صادفة",
    "quafia": "q-ر",
    "engSea": "bassit",
    "arabSea": "البسيط",
    "engTopic": "Short",
    "arabTopic": "قصائد قصيره",
    "poetId": 1808,
    "type": "عموديه",
    "order": 65,
    "link": "https://www.aldiwan.net/poem70895.html",
    "id": 74469
  },
  {
    "name": "حين تختلف العوالي",
    "quafia": "q-ر",
    "engSea": "el-wafer",
    "arabSea": "الوافر",
    "engTopic": "Short",
    "arabTopic": "قصائد قصيره",
    "poetId": 1808,
    "type": "عموديه",
    "order": 66,
    "link": "https://www.aldiwan.net/poem70894.html",
    "id": 74470
  },
  {
    "name": "ولست وإن شاحنت بعض عشيرتي",
    "quafia": "q-ر",
    "engSea": "el-tawil",
    "arabSea": "الطويل",
    "engTopic": "Short",
    "arabTopic": "قصائد قصيره",
    "poetId": 1808,
    "type": "عموديه",
    "order": 67,
    "link": "https://www.aldiwan.net/poem70893.html",
    "id": 74471
  },
  {
    "name": "وتنكرت شيبي فقلت لها",
    "quafia": "q-ي",
    "engSea": "el-kamel",
    "arabSea": "الكامل",
    "engTopic": "Romance",
    "arabTopic": "قصائد رومنسيه",
    "poetId": 1808,
    "type": "عموديه",
    "order": 68,
    "link": "https://www.aldiwan.net/poem70892.html",
    "id": 74472
  },
  {
    "name": "فرأيتها عصلا موقحة",
    "quafia": "q-ر",
    "engSea": "el-kamel",
    "arabSea": "الكامل",
    "engTopic": "Short",
    "arabTopic": "قصائد قصيره",
    "poetId": 1808,
    "type": "عموديه",
    "order": 69,
    "link": "https://www.aldiwan.net/poem70891.html",
    "id": 74473
  },
  {
    "name": "ليالي بعضهم جيران بعض",
    "quafia": "q-ض",
    "engSea": "el-wafer",
    "arabSea": "الوافر",
    "engTopic": "Short",
    "arabTopic": "قصائد قصيره",
    "poetId": 1808,
    "type": "عموديه",
    "order": 70,
    "link": "https://www.aldiwan.net/poem70890.html",
    "id": 74474
  },
  {
    "name": "خليلي إن الرأي فرقه الهوى",
    "quafia": "q-ع",
    "engSea": "el-tawil",
    "arabSea": "الطويل",
    "engTopic": "Parting",
    "arabTopic": "قصائد فراق",
    "poetId": 1808,
    "type": "عموديه",
    "order": 71,
    "link": "https://www.aldiwan.net/poem70889.html",
    "id": 74475
  },
  {
    "name": "وفي غطفان عذق عز ممنع",
    "quafia": "q-ع",
    "engSea": "el-tawil",
    "arabSea": "الطويل",
    "engTopic": "Short",
    "arabTopic": "قصائد قصيره",
    "poetId": 1808,
    "type": "عموديه",
    "order": 72,
    "link": "https://www.aldiwan.net/poem70888.html",
    "id": 74476
  },
  {
    "name": "وجيدا كجيد الآدم الفردراعه",
    "quafia": "q-ع",
    "engSea": "el-tawil",
    "arabSea": "الطويل",
    "engTopic": "Short",
    "arabTopic": "قصائد قصيره",
    "poetId": 1808,
    "type": "عموديه",
    "order": 73,
    "link": "https://www.aldiwan.net/poem70887.html",
    "id": 74477
  },
  {
    "name": "كنخل بأعلى قرح حيط فلم يزل",
    "quafia": "q-ع",
    "engSea": "el-tawil",
    "arabSea": "الطويل",
    "engTopic": "Short",
    "arabTopic": "قصائد قصيره",
    "poetId": 1808,
    "type": "عموديه",
    "order": 74,
    "link": "https://www.aldiwan.net/poem70886.html",
    "id": 74478
  },
  {
    "name": "وتعرف إن ضلت فتهدى لربها",
    "quafia": "q-ع",
    "engSea": "el-tawil",
    "arabSea": "الطويل",
    "engTopic": "Sadness",
    "arabTopic": "قصائد حزينه",
    "poetId": 1808,
    "type": "عموديه",
    "order": 75,
    "link": "https://www.aldiwan.net/poem70885.html",
    "id": 74479
  },
  {
    "name": "مذاويد بالبيض الحديث صقالها",
    "quafia": "q-ف",
    "engSea": "el-tawil",
    "arabSea": "الطويل",
    "engTopic": "Short",
    "arabTopic": "قصائد قصيره",
    "poetId": 1808,
    "type": "عموديه",
    "order": 76,
    "link": "https://www.aldiwan.net/poem70884.html",
    "id": 74480
  },
  {
    "name": "بلاحب كمقد المعن وعسه",
    "quafia": "q-ف",
    "engSea": "bassit",
    "arabSea": "البسيط",
    "engTopic": "Short",
    "arabTopic": "قصائد قصيره",
    "poetId": 1808,
    "type": "عموديه",
    "order": 77,
    "link": "https://www.aldiwan.net/poem70883.html",
    "id": 74481
  },
  {
    "name": "بان الخليط فما للقلب معقول",
    "quafia": "q-ل",
    "engSea": "bassit",
    "arabSea": "البسيط",
    "engTopic": "Romance",
    "arabTopic": "قصائد رومنسيه",
    "poetId": 1808,
    "type": "عموديه",
    "order": 78,
    "link": "https://www.aldiwan.net/poem70882.html",
    "id": 74482
  },
  {
    "name": "كأني ورحلي روحتنا نعامة",
    "quafia": "q-ل",
    "engSea": "el-tawil",
    "arabSea": "الطويل",
    "engTopic": "Short",
    "arabTopic": "قصائد قصيره",
    "poetId": 1808,
    "type": "عموديه",
    "order": 79,
    "link": "https://www.aldiwan.net/poem70881.html",
    "id": 74483
  },
  {
    "name": "كأن سخالها بلوى سمار",
    "quafia": "q-ل",
    "engSea": "el-wafer",
    "arabSea": "الوافر",
    "engTopic": "Short",
    "arabTopic": "قصائد قصيره",
    "poetId": 1808,
    "type": "عموديه",
    "order": 80,
    "link": "https://www.aldiwan.net/poem70880.html",
    "id": 74484
  },
  {
    "name": "ذعرت بجوس نهبلة قذاف",
    "quafia": "q-ل",
    "engSea": "el-wafer",
    "arabSea": "الوافر",
    "engTopic": "Short",
    "arabTopic": "قصائد قصيره",
    "poetId": 1808,
    "type": "عموديه",
    "order": 81,
    "link": "https://www.aldiwan.net/poem70879.html",
    "id": 74485
  },
  {
    "name": "رحلت إليك من جنفاء حتى",
    "quafia": "q-ي",
    "engSea": "el-wafer",
    "arabSea": "الوافر",
    "engTopic": "Short",
    "arabTopic": "قصائد قصيره",
    "poetId": 1808,
    "type": "عموديه",
    "order": 82,
    "link": "https://www.aldiwan.net/poem70878.html",
    "id": 74486
  },
  {
    "name": "أصبح الدهر وقد ألوى بهم",
    "quafia": "q-ل",
    "engSea": "el-raml",
    "arabSea": "الرمل",
    "engTopic": "Short",
    "arabTopic": "قصائد قصيره",
    "poetId": 1808,
    "type": "عموديه",
    "order": 83,
    "link": "https://www.aldiwan.net/poem70877.html",
    "id": 74487
  },
  {
    "name": "ولو تشترى منه لباع ثيابه",
    "quafia": "q-م",
    "engSea": "el-tawil",
    "arabSea": "الطويل",
    "engTopic": "Short",
    "arabTopic": "قصائد قصيره",
    "poetId": 1808,
    "type": "عموديه",
    "order": 84,
    "link": "https://www.aldiwan.net/poem70876.html",
    "id": 74488
  },
  {
    "name": "أمن ظعن هبت بليل فأصبحت",
    "quafia": "q-م",
    "engSea": "el-tawil",
    "arabSea": "الطويل",
    "engTopic": "Short",
    "arabTopic": "قصائد قصيره",
    "poetId": 1808,
    "type": "عموديه",
    "order": 85,
    "link": "https://www.aldiwan.net/poem70875.html",
    "id": 74489
  },
  {
    "name": "عوازب لم تسمع نبوح مقامة",
    "quafia": "q-م",
    "engSea": "el-tawil",
    "arabSea": "الطويل",
    "engTopic": "Short",
    "arabTopic": "قصائد قصيره",
    "poetId": 1808,
    "type": "عموديه",
    "order": 86,
    "link": "https://www.aldiwan.net/poem70874.html",
    "id": 74490
  },
  {
    "name": "وقدر ككف القرد لا مستعيرها",
    "quafia": "q-م",
    "engSea": "el-tawil",
    "arabSea": "الطويل",
    "engTopic": "Short",
    "arabTopic": "قصائد قصيره",
    "poetId": 1808,
    "type": "عموديه",
    "order": 87,
    "link": "https://www.aldiwan.net/poem70873.html",
    "id": 74491
  },
  {
    "name": "فلو قبل مبكاها بكيت صبابة",
    "quafia": "q-م",
    "engSea": "el-tawil",
    "arabSea": "الطويل",
    "engTopic": "Short",
    "arabTopic": "قصائد قصيره",
    "poetId": 1808,
    "type": "عموديه",
    "order": 88,
    "link": "https://www.aldiwan.net/poem70872.html",
    "id": 74492
  },
  {
    "name": "وافى الخيال وما وافاك من أمم",
    "quafia": "q-م",
    "engSea": "bassit",
    "arabSea": "البسيط",
    "engTopic": "Short",
    "arabTopic": "قصائد قصيره",
    "poetId": 1808,
    "type": "عموديه",
    "order": 89,
    "link": "https://www.aldiwan.net/poem70871.html",
    "id": 74493
  },
  {
    "name": "يسقي بأجداد عاد هملا رغدا",
    "quafia": "q-م",
    "engSea": "bassit",
    "arabSea": "البسيط",
    "engTopic": "Short",
    "arabTopic": "قصائد قصيره",
    "poetId": 1808,
    "type": "عموديه",
    "order": 90,
    "link": "https://www.aldiwan.net/poem70870.html",
    "id": 74494
  },
  {
    "name": "أما الرواء ففينا حد ترئية",
    "quafia": "q-م",
    "engSea": "bassit",
    "arabSea": "البسيط",
    "engTopic": "Satire",
    "arabTopic": "قصائد هجاء",
    "poetId": 1808,
    "type": "عموديه",
    "order": 91,
    "link": "https://www.aldiwan.net/poem70869.html",
    "id": 74495
  },
  {
    "name": "حي دار الحي لا دار بها",
    "quafia": "q-م",
    "engSea": "el-raml",
    "arabSea": "الرمل",
    "engTopic": "Short",
    "arabTopic": "قصائد قصيره",
    "poetId": 1808,
    "type": "عموديه",
    "order": 92,
    "link": "https://www.aldiwan.net/poem70868.html",
    "id": 74496
  },
  {
    "name": "هزئت مية أن ضاحكتها",
    "quafia": "q-م",
    "engSea": "el-raml",
    "arabSea": "الرمل",
    "engTopic": "Satire",
    "arabTopic": "قصائد هجاء",
    "poetId": 1808,
    "type": "عموديه",
    "order": 93,
    "link": "https://www.aldiwan.net/poem70867.html",
    "id": 74497
  },
  {
    "name": "يزع الدارع منه مثل ما",
    "quafia": "q-م",
    "engSea": "el-raml",
    "arabSea": "الرمل",
    "engTopic": "Short",
    "arabTopic": "قصائد قصيره",
    "poetId": 1808,
    "type": "عموديه",
    "order": 94,
    "link": "https://www.aldiwan.net/poem70866.html",
    "id": 74498
  },
  {
    "name": "لقد تقوس لحييه ولمته",
    "quafia": "q-ن",
    "engSea": "bassit",
    "arabSea": "البسيط",
    "engTopic": "Short",
    "arabTopic": "قصائد قصيره",
    "poetId": 1808,
    "type": "عموديه",
    "order": 95,
    "link": "https://www.aldiwan.net/poem70865.html",
    "id": 74499
  },
  {
    "name": "تخوف السير منها تامكا قردا",
    "quafia": "q-ن",
    "engSea": "bassit",
    "arabSea": "البسيط",
    "engTopic": "Short",
    "arabTopic": "قصائد قصيره",
    "poetId": 1808,
    "type": "عموديه",
    "order": 96,
    "link": "https://www.aldiwan.net/poem70864.html",
    "id": 74500
  },
  {
    "name": "هتاك أخبية ولاج أبوبة",
    "quafia": "q-ن",
    "engSea": "bassit",
    "arabSea": "البسيط",
    "engTopic": "Reproach",
    "arabTopic": "قصائد عتاب",
    "poetId": 1808,
    "type": "عموديه",
    "order": 97,
    "link": "https://www.aldiwan.net/poem70863.html",
    "id": 74501
  },
  {
    "name": "زارتك من دونها شرج وحرته",
    "quafia": "q-ن",
    "engSea": "bassit",
    "arabSea": "البسيط",
    "engTopic": "Short",
    "arabTopic": "قصائد قصيره",
    "poetId": 1808,
    "type": "عموديه",
    "order": 98,
    "link": "https://www.aldiwan.net/poem70862.html",
    "id": 74502
  },
  {
    "name": "ألا ناديا ربعي كبيشة باللوى",
    "quafia": "q-ي",
    "engSea": "el-tawil",
    "arabSea": "الطويل",
    "engTopic": "Sadness",
    "arabTopic": "قصائد حزينه",
    "poetId": 1808,
    "type": "عموديه",
    "order": 99,
    "link": "https://www.aldiwan.net/poem70861.html",
    "id": 74503
  },
  {
    "name": "بني عامر ما تأمرون بشاعر",
    "quafia": "q-ي",
    "engSea": "el-tawil",
    "arabSea": "الطويل",
    "engTopic": "Reproach",
    "arabTopic": "قصائد عتاب",
    "poetId": 1808,
    "type": "عموديه",
    "order": 100,
    "link": "https://www.aldiwan.net/poem70860.html",
    "id": 74504
  },
  {
    "name": "أحقا أتاني أن عوف بن مالك",
    "quafia": "q-ي",
    "engSea": "el-tawil",
    "arabSea": "الطويل",
    "engTopic": "Praise",
    "arabTopic": "قصائد مدح",
    "poetId": 1808,
    "type": "عموديه",
    "order": 101,
    "link": "https://www.aldiwan.net/poem70859.html",
    "id": 74505
  },
  {
    "name": "إن الخليفة ماء لست قاربه",
    "quafia": "q-ي",
    "engSea": "bassit",
    "arabSea": "البسيط",
    "engTopic": "General",
    "arabTopic": "قصائد عامه",
    "poetId": 1808,
    "type": "عموديه",
    "order": 102,
    "link": "https://www.aldiwan.net/poem70805.html",
    "id": 74506
  }
]